{"8721055490531":{"naam":"Sentio - mini parfum - Congrats! - heren - vaderdag - eau de toilette - 15 ml","ts":1776575703424},"6151030861827":{"naam":"NG Lightness Eau de Parfum 100ml met 5ml hervulbare tasverstuiver","ts":1776573067949},"7640158816332":{"naam":"Sentio Blossoms of Joy Sweet miniparfum eau de parfum 15 ml.","ts":1776573068143},"7640158816349":{"naam":"Sentio Blossoms of Joy Wild miniparfum eau de parfum 15 ml.","ts":1776573068342},"6291012002739":{"naam":"Dorall Giftset Miss Blossom voor dames","ts":1776573068544},"8715658401643":{"naam":"Linn Young - Her Desire Women - Eau de Parfum - 100ML","ts":1776573068735},"6013900439423":{"naam":"Green Nature Aloe Vera Body Cream 250ml","ts":1776573069134},"6291012004931":{"naam":"Dorall geschenkset Heren Parfum Entice Play Giftset 100ml + 15ml edt sh+aft","ts":1776573069336},"8719214755003":{"naam":"NG Femme Brilliant Eau de Parfum 100 ml - Next Generation","ts":1776573069546},"8715658420088":{"naam":"Georges Mezotti You're Perfect Honey Edp 100ml","ts":1776573069771},"7640158816752":{"naam":"Hello Kitty-Cool & Sweet-15ml Eau de Parfum","ts":1776573070369},"7640158817827":{"naam":"Sentio Happy Birthday To You miniparfum eau de parfum for unisex 15ml","ts":1776573070577},"4042342003031":{"naam":"Shiatsu feromonen parfum (vrouw) 15 ml","ts":1776573070773},"6151030129156":{"naam":"NG Serene Path Eau de Parfum 100ml met 5ml hervulbare tasverstuiver","ts":1776573070975},"8719214759681":{"naam":"NG Perfume Stick - MISS PERFECT - 10gr","ts":1776573071169},"7640158816363":{"naam":"Sentio Blossoms of Joy Dazzling miniparfum eau de parfum 15 ml.","ts":1776573071369},"8718421831425":{"naam":"NG Homme for Men Eau de Toilette 100 ml","ts":1776575650851},"6151030387365":{"naam":"NG Burnt Vanilla Eau de Parfum 100ml met 5ml hervulbare tasverstuiver","ts":1776573068927},"6151030483418":{"naam":"NG Predator Elegance Eau de Parfum 100ml met 5ml hervulbare tasverstuiver","ts":1776573071752},"6291012007161":{"naam":"Creation Lamis Fatal Snake Magical Giftset for women","ts":1776573071950},"7640158815618":{"naam":"Sentio Giftset-Involved pour homme-Eau de Toilette en Showergel","ts":1776573074357},"8719214751920":{"naam":"NG Heavens Body 100ML Dames Eau de Parfum","ts":1776573184430},"8714319228889":{"naam":"Amando Noir Eau de Toilette - 50 ml","ts":1775917680949},"6151030588595":{"naam":"NG Mrs. Unique Eau de Parfum 100ml met 5ml hervulbare tasverstuiver","ts":1776573181414},"7640158817322":{"naam":"Sentio Blossom Kiss Eau De Parfum - 100 ml","ts":1776573072542},"7640158817735":{"naam":"Sentio Eclaire Eau De Parfum - 100 ml","ts":1776573072740},"6291012871038":{"naam":"Savanna Nights - eau de toilette","ts":1776573123385},"8721055496632":{"naam":"Sentio Mary Davina Cristal parfum - eau de parfum spray voor dames - 100 ml","ts":1776575710757},"7640158817995":{"naam":"Sentio Flare parfum - Sensuele eau de parfum met frisse en bloemige tonen - 100 ml","ts":1776575710332},"6013900194148":{"naam":"NG Touch Eau de Parfum 80ml + 15ml","ts":1776573073355},"6291012005525":{"naam":"Creation Lamis Giftset - Midnight Leather - for Men","ts":1776573073756},"8715658999799":{"naam":"Eau de Toilette-Liquid-Steel-100 ML - Mannen","ts":1776573073955},"6151028322347":{"naam":"NG Home Perfume - Next Fragrance - Set van 3st","ts":1776573070168},"8715658401049":{"naam":"Linn Young - Acqua - Eau de parfum - 100ML","ts":1776573074146},"8719214759711":{"naam":"NG - EMPERESS DESIRE - 100ml Eau de Parfum for Women","ts":1776573074550},"8714319237768":{"naam":"Therme Aqua Wellness Fragrance Sticks 100ml -","ts":1776573074753},"8715658390084":{"naam":"Linn Young - Young Pure Lucky Lady - Eau De Parfum - 100Ml","ts":1776573074952},"8719214757380":{"naam":"NG Spectre Fragrances Floret for her eau de parfum 100ml","ts":1776573075162},"8719214754808":{"naam":"MEEKA Shower Foam Pure Silver 225ml","ts":1776573075355},"7640158817247":{"naam":"Sentio Single Lady Geschenkset - Luxe bad- en douchegel, bodylotion, bodyspray","ts":1776573075548},"7640158815793":{"naam":"Sentio Parfum Life Like Bella Eau de Parfum for her 35ml","ts":1776573075740},"8715658380689":{"naam":"Omerta -X Emotion- Eau de Parfum 100ml","ts":1776573183022},"8714319237379":{"naam":"Therme Geurstokjes Zen by Night 100 ml","ts":1776573075944},"8721055491392":{"naam":"Sentio Rich Tabacco Blend Unisex Eau de Parfum 100ml","ts":1776573076139},"8714319236983":{"naam":"Therme Geurstokjes Mystic Rose - 100 ml","ts":1776575764940},"6151027816809":{"naam":"NG Home Predator Geurstokjes 200ml","ts":1776573076536},"8719214750633":{"naam":"Ng Valencia Women parfum - Bloemige eau de parfum voor dames - 100 ml","ts":1776573076924},"7640158817551":{"naam":"Sentio Mrs. Glam Eau de Parfum For Her 35ml","ts":1776573077124},"7640158815878":{"naam":"Sentio Raja Eau de Parfum for her 35ml","ts":1776573077335},"8721055491101":{"naam":"Sentio Parfum Mon Passage Eau de Parfum for her 35ml","ts":1776573077530},"6151029534541":{"naam":"NG Bella Vida Eau de Parfum 80 ml met 5ml hervulbare tasverstuiver","ts":1776573120880},"8721055491088":{"naam":"Sentio Parfum Goddessa Eau de Parfum for her 35ml","ts":1776573185835},"8715658360087":{"naam":"Real Time Trespassing Lady Night Edition 100 ml - Eau de Parfum - Damesparfum","ts":1776573121161},"8714319258862":{"naam":"Therme Home Perfume Sticks Orange Happiness - 150 ml","ts":1776573121358},"8715658390350":{"naam":"Linn Young - Club 420 Exclusive Black Men - Eau de toilette - 100ML","ts":1776573121559},"8715658009245":{"naam":"Real Time - Si Femme Chic - Eau de parfum - 100ML","ts":1776573121753},"8721349102720":{"naam":"Azira - Royal Oud - Eau de Parfum Unisex","ts":1776573121952},"7640158818879":{"naam":"Sentio Paradise Miniparfum Cote D'Azur Romance eau de parfum for women 15 ml","ts":1776573122347},"8719214759186":{"naam":"NG - Next Generation - Mrs. Unique for her miniparfum eau de parfum 15ml","ts":1776573122537},"7640158814802":{"naam":"Sentio Attractive Life Eau De Parfum - 100 ml","ts":1776573072934},"7640158815694":{"naam":"Sentio Chalize Eau De Parfum - 100 ml","ts":1776573122770},"8715658361633":{"naam":"Real Time Liberty Life Manhattan 100ml Eau de Parfum","ts":1776573122962},"8721055497011":{"naam":"De La Mare Blueberry - Bosbes Geur - For Women Eau de Parfum 15 ml","ts":1776575708474},"7640158816356":{"naam":"Sentio Blossoms of Joy Pretty miniparfum eau de parfum 15 ml.","ts":1776573123603},"5414666005722":{"naam":"Dorall Xstasy eau de parfum 100ml","ts":1776573123801},"7640158817858":{"naam":"Sentio Stay Wild Unbound miniparfum eau de parfum for woman 15ml","ts":1776573124204},"8719214754341":{"naam":"MEEKA Shower Foam Giftset","ts":1776573124409},"8715658350217":{"naam":"Real Time - Submarine The Fragrance For Men - Eau De Toilette - 100ML","ts":1776573124600},"6291012876583":{"naam":"Doral Collection Ville De L'amour parfum - Eau de parfum - 100 ml","ts":1776573124800},"8715658360032":{"naam":"Real Time - La Passion En Pink - Eau De Parfum - 100ML","ts":1776573124996},"8715658002543":{"naam":"Real Time - Papillon & Fleurs For Women - Eau De Parfum - 100ML","ts":1776573125194},"8721055493327":{"naam":"Hello Kitty Club Parfum set 3 stuks voor kinderen - Meisjes","ts":1776575707460},"8715658361534":{"naam":"Real Time - Love You Sweet Kiss - 15ml Eau de Parfum","ts":1776573125617},"7640158818015":{"naam":"Sentio Living Legend Eau de Toilette - 100 ml","ts":1776573125814},"8715658400707":{"naam":"Linn Young - Club 420 Gold Exclusive Women - Eau de parfum - 100ML","ts":1776573126007},"8715658360193":{"naam":"Real Time - Hello Miss! - Eau De Parfum - 100ML","ts":1776573126203},"7640158814864":{"naam":"Sentio Dazzling Lady Eau De Parfum - 100 ml","ts":1776573126414},"8715658013006":{"naam":"Street Looks - Fleurette - Eau de parfum - 100ML","ts":1776573181801},"6013912137126":{"naam":"Egyptian Powder HORUS 17gr + luxe borstel","ts":1776573126823},"7640158815557":{"naam":"Sentio Attractive Life Geschenkset - 1 set","ts":1776573127010},"7640158817476":{"naam":"SENTIO Happy Holidays Eau de Parfum 15 ml - Miniparfum - Kerst Parfum - Bloemig - Fruitig - Vanillenoot - Jasmijn - Koffie","ts":1776573127402},"8721055494539":{"naam":"Sentio Sugar Charm eau de parfum unisex 15 ml","ts":1776573127595},"8719214758530":{"naam":"NG Darkness for Men Giftset","ts":1776573127792},"8715658401605":{"naam":"Linn Young Admiration Eternal Rose Absolu for woman edp 100ml","ts":1776573128190},"8715658400417":{"naam":"Linn - Young Oui Je T'Aime Mon Amour - Eau De Parfum - 100Ml","ts":1776573184226},"8721055498469":{"naam":"SENTIO DE LA MARE YAKIRA BODYMIST 250ML FROSTED LYCHEE FRESH SPARKLING/28","ts":1776573128389},"8715658350255":{"naam":"Real Time - Racing Horse Gold - Eau de toilette - 100ML","ts":1776573128586},"8715658009566":{"naam":"Real Time - Black Warrior - Eau De Parfum - 100Ml","ts":1776573181987},"8715658008569":{"naam":"Real Time - Sense & Emotion For Women - Eau De Parfum - 100ML","ts":1776573128972},"8721349102706":{"naam":"Azira - Dream Oasis - Eau de Parfum Unisex","ts":1776573129173},"8721055498452":{"naam":"SENTIO DE LA MARE YAKIRA BODYMIST 250ML TACHIO WONDER BOLD CHARM/14","ts":1776573129371},"8721055490371":{"naam":"Parfum SENTIO Lucky Numbers 24 Twentyfour Seven eau de parfum 15ml","ts":1776573129574},"8715658999645":{"naam":"Omerta - Miss Senible - Eau de parfum - 100","ts":1776573129769},"8715658997443":{"naam":"Omerta - Ma Merveilleuse - Eau De Parfum - 100ML","ts":1776573130164},"6013909650621":{"naam":"NG Predator for Women 100ml + 15ml Eau de Parfum","ts":1776573130365},"6013902431449":{"naam":"NG Next Fragrance Eau de Parfum 100ml + 15ml","ts":1776573130588},"8721349102669":{"naam":"Azira - ALMAS ABSOLU - Eau de Parfum Unisex","ts":1776573130789},"8721349102744":{"naam":"Azira - Sable Musk - Eau de Parfum Unisex","ts":1776573180593},"8719214753290":{"naam":"NG Femme L'odeur du NG Giftset","ts":1776573181608},"8715658370550":{"naam":"Omerta - Conclude Oud Orient Perfection - Eau De Parfum - 100ML","ts":1776573187015},"8719214759674":{"naam":"NG Perfume Stick - PREDATOR - 10gr","ts":1776573182215},"6013910468482":{"naam":"NG Homme 100ml + 15ml Eau De Toilette","ts":1776573182407},"8715658390237":{"naam":"Linn Young Blue Window - Eau de Toilette voor dames - 100ML","ts":1776573180999},"8715658390954":{"naam":"Linn Young Admiration Eternal Glorious Day - Eau de Toilette voor heren - 100ML","ts":1776573182597},"7640158816295":{"naam":"Sentio Black Grenade Eau de Toilette - Kruidige en houtachtige geur voor heren - 100 ml","ts":1776573187210},"6291012004825":{"naam":"Creation Lamis Diable Bleu Giftset Unisex","ts":1776573182792},"8715658002536":{"naam":"Real Time - Love & Rozes - Eau De Parfum - 100ML","ts":1776573183412},"7640158814925":{"naam":"Sentio Single Lady parfum - Eau de parfum voor de moderne vrouw - 100 ml","ts":1776573183607},"5414666001366":{"naam":"Creation Lamis Diable Bleu parfum - Oriëntaalse en houtige eau de parfum voor dames","ts":1776575651277},"8721055494218":{"naam":"Bubble Bliss Like a Fairytale - Parfum Set Van 6 Stuks - Eau de Parfum Voor Kinderen - 6x15ml","ts":1776575705271},"8721055498131":{"naam":"De La Mare Parfum Raggio Di Sole 36 Berry & Amber Plum Eau de Parfum 100 ml","ts":1776573183807},"8721055493648":{"naam":"DLM Engage Eau de Toilette 100 ml for men","ts":1776573184033},"8715658390220":{"naam":"Linn Young Wild Adventure Eau De Toilette Spray 100ml","ts":1776573181223},"8715658370260":{"naam":"Omerta - Royal X - Eau de toilette - 100ML","ts":1776573184619},"8719214757823":{"naam":"NG Bella Vida Giftset 3pcs - Parfum - Showergel - Bodylotion - voor Dames","ts":1776573185255},"8721055492665":{"naam":"SENTIO Warme wensen! And Cozy Kisses Eau de Parfum 15 ml - Miniparfum - Love - Liefde - Cadeau - Bloemig - Houtig - Comfort","ts":1776573185450},"8719214754549":{"naam":"NG Home Bella Vida Geurstokjes 200ml","ts":1776573185637},"8715658361602":{"naam":"Real Time - Pink Sorbet - Eau De Parfum - 100ML","ts":1776575765563},"8715658361435":{"naam":"Real Time - Blooming Flower Nectar - Eau De Parfum - 100ML","ts":1776573186211},"8715658002932":{"naam":"Real Time King Sky Eau de Toilette 100ml","ts":1776573186613},"8715658360971":{"naam":"Real Time - Please Call Me - Eau de parfum - 100ML","ts":1776573072143},"8721055492245":{"naam":"Bubble Bliss Unicorn Giftbook Parfum Dreamy Glitterwings EDP voor meisjes 50ml","ts":1776573187416},"8721055494300":{"naam":"Bubble Bliss Blooming Bella Parfum Giftbag - Eau de parfum voor meisjes 50ml","ts":1776573126627},"8721055493747":{"naam":"Sentio Love & Casual for Everyone Eau de Parfum Spray 100 ml","ts":1776573187609},"8721055496656":{"naam":"Sentio Mary Davina Liora parfum - Eau de parfum spray voor dames - 100 ml","ts":1776573187813},"6291012004955":{"naam":"Dorall geschenkset /Giftset Manipulare for men 100ml + 15ml edt + 50ml aftershave balm + 50ml shower gel","ts":1776573188010},"8721055494003":{"naam":"Bubble Bliss - Giftset - You're Flamazing - Showergel + Eau de Parfum - Cadeauset voor Kinderen - Geschenkset","ts":1776573188205},"6291012905726":{"naam":"Dorall -Le Homme Noir- Eau de Toilette 100ml","ts":1776573188413},"6291012004948":{"naam":"Dorall Collection L’Homme geschenkset heren parfum - 115ml edt + 100ml After Shawer","ts":1776573188613},"8721055496977":{"naam":"De La Mare Vanilla parfum - Romige vanille geur voor vrouwen - 15 ml","ts":1776573188808},"6151010165129":{"naam":"NG - Bella Vida - Eau de Parfum 80 ml voor dames","ts":1776573189008},"8719214750114":{"naam":"NG - PREDATOR ELEGANCE - Eau de Parfum 100ml","ts":1776573189200},"8721055498155":{"naam":"De La Mare Parfum Raggio Di Sole 49 Caramel & Pistachio Eau de Parfum 100 ml","ts":1776573189397},"8715658012900":{"naam":"Real Time - Loveliness Sensuelle - Eau De Parfum - 100ML","ts":1776573189602},"8721055497554":{"naam":"Sentio Verjux Pure Urban Unisex Eau de Parfum 100ml","ts":1776573189794},"8721055497530":{"naam":"Sentio Verjux Orchesta Unisex Eau de Parfum 100ml","ts":1776573189998},"5414666001588":{"naam":"Fatal Snake Magical - Eau de Parfum 100 ml.","ts":1776573190189},"8715658380856":{"naam":"Omerta - OH SO! Scarlet Fire - Eau De Parfum - 100ML","ts":1776573190400},"8719214756550":{"naam":"TBY - To Be Pleased - 100ml Eau de Parfum voor vrouwen","ts":1776573240194},"7640158817797":{"naam":"Sentio May All Your Wishes Come True miniparfum eau de parfum for woman 15ml","ts":1776573240380},"6096035172106":{"naam":"Real Time |Pearly passion | Eau de parfum voor haar","ts":1776573240586},"8715658390770":{"naam":"Linn Young Techno Tronics Men Giftset Eau de Toilette 100ml + 30ml","ts":1776573240785},"8719214753009":{"naam":"NG Perfumes Golddigger Woman eau de parfum 90 ml","ts":1776573241025},"8715658002727":{"naam":"Real Time - Club United Men & Women - Eau De Toilette - 100ML","ts":1776573241217},"8715658009573":{"naam":"Real Time Big Eagle Black Eau de Toilette 100ml","ts":1776573241409},"7640158816141":{"naam":"Sentio Best Friend Ever eau de parfum voor vrouwen - 15ml","ts":1776573241601},"8721055494522":{"naam":"Sentio Banana Dream eau de parfum unisex 15 ml","ts":1776573241809},"8715658009771":{"naam":"Real Time - Sexy Dentelle For Woman - Eau de parfum - 100ML","ts":1776573242002},"8721055492634":{"naam":"SENTIO Joy to the World Eau de Parfum 15 ml - Miniparfum - Kerst - Cadeau - Fris - Frisse geur","ts":1776573242202},"8715658002871":{"naam":"Real Time - Blue Fog - Eau De Toilette - 100ML","ts":1776573242401},"8721055492603":{"naam":"SENTIO FEESTDAGEN PINK - Warm Wishes! And Cozy Kisses - Body Mist 250ml","ts":1776573242599},"8719214758448":{"naam":"NG Darkness for Men Eau de Toilette 15ml","ts":1776573242795},"8721055492368":{"naam":"Vibezz-Scentique-Eau de Parfum For Her-100ml","ts":1776573242991},"8721055498476":{"naam":"SENTIO DE LA MARE YAKIRA BODYMIST 250ML MELLOW CLOUD DELICATE SWEET/ 75","ts":1776573243201},"8715658360674":{"naam":"Real Time - Me My Life My Perfume - Eau De Parfum - 100ML","ts":1776573243424},"8715658013426":{"naam":"Real Time - My Flower - Eau De Parfum - 100ML","ts":1776573243630},"7640158815243":{"naam":"Sentio Patron Pour Homme Eau de Toilette For Men 15ml","ts":1776573243871},"8715658401513":{"naam":"Linn Young - Sexy To Someone Unisex - Eau de Parfum 100ml","ts":1776573244086},"8721055490692":{"naam":"Sentio Floricci Giallo miniparfum eau de parfum 15ml","ts":1776573244278},"7640158815267":{"naam":"Sentio Involved Pour Homme Eau de Toilette For Men 15ml","ts":1776573244488},"8721055490357":{"naam":"Parfum SENTIO Lucky Numbers 10 You're A Ten eau de parfum 15ml","ts":1776573244826},"8720938379246":{"naam":"Omerta - Romantic Love Pack - set van 3x100ml","ts":1775917984328},"8715658997481":{"naam":"Linn Young - Pure Luck Eau De Toilette 100ML","ts":1776573245018},"8719214758325":{"naam":"NG Axure Sport Eau de Toilette 100ml","ts":1776573123166},"8715658401339":{"naam":"Linn Young -Oud Elixir d'Extase Pink Label Giftset- Eau de parfum 100ml + 30ml","ts":1776573245212},"7640158816165":{"naam":"Sentio Quote2 cadeau idee tekst for women - You Are My Nr. 1 - Eau de parfum - 15ml","ts":1776573245448},"5414666016674":{"naam":"Checkered Flag - 100 ml.","ts":1776573245647},"8721055494553":{"naam":"Sentio Applemelon Splash eau de parfum unisex 15 ml","ts":1776573245837},"8715658969594":{"naam":"Linn Young \"Oso Perfect Men\" Eau de Toilette 100ml","ts":1776573246028},"5414666015851":{"naam":"Dorall -Exotic Vanilla- Eau de Toilette spray 100ml for women","ts":1776573246230},"8715658401216":{"naam":"Linn Young - Oud Elixir d'Extase Red Label - Eau de parfum - 100ML","ts":1776573246458},"6291012879218":{"naam":"Dorall-Hunted- Eau de Toilette 100ml","ts":1776573246661},"7640158816127":{"naam":"Sentio Woohoo! Congrats! parfum - Eau de parfum voor vrouwen - 15ml","ts":1776573246866},"8715658401490":{"naam":"Linn Young - Hot Cherry Unisex - Eau de Parfum 100ml","ts":1776573247058},"8715658998686":{"naam":"Linn Young - Nature's Sexy - Eau de parfum - 100","ts":1776573247244},"8715658361008":{"naam":"Real Time - Hunted For Women - Eau de parfum - 100ML","ts":1776573247433},"8721055493945":{"naam":"Bubble Bliss - Fantastic Flamingo - Feathered Fun - Eau de Parfum - Voor Kinderen 15ml","ts":1776573247641},"8719214752699":{"naam":"Next Generation Touch Desire Eau de Parfum 80ml","ts":1776573247838},"8719214754815":{"naam":"MEEKA Shower Foam Pure Bronze 225ml","ts":1776573248031},"8721055491798":{"naam":"Sentio Spin Me Round Eau de Parfum For Her 50ml","ts":1776573248278},"7640158816486":{"naam":"Sentio Zodiac - Aries - Ram - Eau De Parfum - For Women - 15ml","ts":1776573248483},"8715658360759":{"naam":"Real Time Loveliness La Passione - Eau de parfum - 100ML","ts":1776573180785},"8715658002574":{"naam":"Real Time - Kindlooks For Women - Eau de parfum - 100","ts":1776573248874},"8715658350736":{"naam":"Real Time Tempting Rumors 100ml Eau de Toilette For Men","ts":1776573249069},"8721055493846":{"naam":"Bubble Bliss - Unicorn Sprinkles - Believe - Lika a Unicorn - eau de parfum - voor kinderen 15ml","ts":1776573249286},"7640158817896":{"naam":"Sentio Stay Wild Untamed miniparfum eau de parfum for woman 15ml","ts":1776573249498},"8721055490333":{"naam":"Sentio Lucky Numbers 7 Lucky Seven parfum - eau de parfum - 15ml","ts":1776573249702},"7640158817872":{"naam":"Sentio Stay Wild Independent Eau de Parfum 15ml voor dames","ts":1776573249900},"5414666007696":{"naam":"Creatuin Lamis Arrivederci - 100 ml - Eau de Toilette voor mannen","ts":1776573250098},"8715658380238":{"naam":"Omerta Express Sensualite Frivole 100ml Eau de Parfum","ts":1776573250332},"6291012884939":{"naam":"Creation Lamis Chortle Eau de Parfum for women 100ml","ts":1776573300154},"8721055493952":{"naam":"Bubble Bliss - Fantastic Flamingo - Fluff & Flutter - Eau de Parfum - Voor Kinderen 15ml","ts":1776573300348},"8715658010562":{"naam":"Georges Mezotti - Expedition Experience Silver Edition - Eau De Toilette - 100ML","ts":1776573300550},"8715658360667":{"naam":"Real Time - Reve Eternelle For Women - Eau De Parfum - 100ML","ts":1776573300751},"8715658390398":{"naam":"Linn Young Pure Luck Men Giftset Eau de parfum 100ml + 30ml","ts":1776573300948},"8719214756895":{"naam":"NG - SERENE PATH - 100ml Eau de Parfum for Women","ts":1776573301135},"8715658360056":{"naam":"Real Time Love You Red 100 ml - Eau de Parfum - Damesparfum","ts":1776573301354},"8715658400752":{"naam":"Linn Young -Club 420 Gold Giftset- Eau de parfum 100ml + 30ml","ts":1776573301546},"8715658969679":{"naam":"Georges Mezotti - Base Track Pure Senses - Eau de toilette - 100ML","ts":1776573301739},"8715658390701":{"naam":"Linn Young Club 420 City Men Giftset Eau de Toilette 100ml + 30ml","ts":1776573301927},"8715658390299":{"naam":"Linn - Young Cross Country - Eau De Toilette - 100Ml","ts":1776573302125},"7640158815021":{"naam":"Sentio Inter Feer men Eau de toilette spray for him 100ml","ts":1776573302357},"8721055493341":{"naam":"Hello Kitty Club Eau de Parfum voor Kinderen 50 ml - You Go Girl!","ts":1776573302561},"8719214753283":{"naam":"NG Predator Giftset","ts":1776573302760},"6013908853870":{"naam":"NG Dominatio Women Eau de Parfum 100ml + 15ml","ts":1776573302958},"8715658999225":{"naam":"Linn Young - Work@holics Club - Eau De Toilette - 100ML","ts":1776573303161},"8715658401322":{"naam":"Linn Young -Oud Elixir d'Extase Red Label Giftset- Eau de parfum 100ml + 30ml","ts":1776573303371},"8715658400769":{"naam":"Linn Young -Club 420 Exclusive Pink Giftset- 100ml + 30ml Eau de parfum","ts":1776573303587},"8715658410010":{"naam":"Georges Mezotti - Go Your Own Direction - Eau De Toilette - 100ML","ts":1776573303816},"7438235516561":{"naam":"To Be Yours For Women - Dames Parfum - 100ml - Eau de Parfum - NG Perfume + Cadeau","ts":1776573304007},"8715658401056":{"naam":"Linn Young - The One Beyond Pink - Eau de parfum - 100ML","ts":1776573304238},"7640158816073":{"naam":"Sentio Ex Plode Dust eau de parfum Miniparfum for women 15 ml","ts":1776573304426},"8715658390923":{"naam":"Linn Young - OSO Perfect Elixir - Eau De Toilette - 100ML for men","ts":1776573304644},"8715658390053":{"naam":"Linn Young - Young Oui Je T'Aime - Eau De Parfum - 100Ml","ts":1776573304850},"8721055495789":{"naam":"Atelier Privee Mistical France Unisex - Dreamy Tonka - Eau de Parfum - 100ml","ts":1775966175949},"8715658361626":{"naam":"Real Time Liberty Life Long Island 100ml Eau de Parfum","ts":1776573305050},"8715658997436":{"naam":"Omerta Pure E-motion Eau de Toilette 100ml","ts":1776573305273},"7640158816998":{"naam":"Hello Kitty - Giftset - Unicorn Rainbow - Showergel + Water-Based Parfum - Cadeauset voor Kinderen - Geschenkset","ts":1776573305463},"8718421831784":{"naam":"MEEKA Summer for Women - 100 ml EDP","ts":1776573305659},"8721055493150":{"naam":"Hello Kitty-Vanilla Scent-15ml Eau de Parfum","ts":1776573305849},"8721055493334":{"naam":"Hello Kitty Club Eau de Parfum voor Kinderen 50 ml - Girls Power","ts":1776573306049},"7640158814840":{"naam":"Sentio Interfeer Eau De Parfum - 100 ml","ts":1776573306248},"8719214756574":{"naam":"TBY - To Be Uniquer - 100ml Eau de Parfum voor vrouwen","ts":1776573306460},"8715658390787":{"naam":"Linn Young Wild Adventure Absolu Men Giftset Eau de Toilette 100ml + 30ml","ts":1776573306655},"6151029299235":{"naam":"Creation Lamis Lorenzo Silvetto Giftset for her","ts":1776573306843},"6291012005969":{"naam":"Creation Lamis Pluton for men Eau de Toilette","ts":1776573076731},"8715658370536":{"naam":"Omerta - Conclude Oud Black Edition - Eau De Parfum - 100ML","ts":1776573307042},"8715658380702":{"naam":"Omerta - Laverder Fields - Eau de Parfum - 100ml","ts":1776573307233},"8721055493112":{"naam":"Hello Kitty-Coconut Scent-15ml Eau de Parfum","ts":1776573307429},"6151027630672":{"naam":"NG Home Perfume Next Fragrance 200ml Spray","ts":1776573307629},"7640158817902":{"naam":"Sentio Stay Wild Fearless miniparfum eau de parfum for woman 15ml","ts":1776573307822},"8721055494256":{"naam":"Bubble Bliss - Like a Fairytale - Blooming Bella - Eau de Parfum - Prinsessen Voor Kinderen 15ml","ts":1776573308019},"8721055493426":{"naam":"Hello Kitty - Giftset - Rainbow - Showergel + Eau de Parfum - Cadeauset voor Kinderen - Geschenkset","ts":1776573308220},"7640158814901":{"naam":"Sentio Confirmation Eau De Parfum - 100 ml","ts":1776573308423},"8715658010395":{"naam":"Georges Mezotti - Crime Perfect Crime - Eau De Toilette - 100ML","ts":1776573308617},"7640158818855":{"naam":"Sentio Paradise Miniparfum Hawaï Waves eau de parfum for women 15 ml","ts":1776573308830},"7640158816004":{"naam":"Sentio Blomicci Violet miniparfum eau de parfum for woman 15ml","ts":1776573309029},"8715658400905":{"naam":"Linn Young - Pure Luck Lady Love - Eau de parfum - 100ML","ts":1776573309228},"8715658400721":{"naam":"Linn - Young Rosiale - Eau De Parfum - 100Ml","ts":1776573309421},"8715658401278":{"naam":"Linn Young - Techno Tronics L'elixer Woman - Eau de parfum - 100ML","ts":1776573309610},"8715658010579":{"naam":"Georges Mezotti - Silver Men - Eau De Toilette - 100ML","ts":1776573309799},"5414666015233":{"naam":"Dorall -Crown Black- Eau de Toilette 100ml","ts":1776573309999},"8715658400714":{"naam":"Linn Young - Club 420 Pink Exclusive Women - Eau de parfum - 100ML","ts":1776573361956},"8715658350224":{"naam":"Real Time Wild Action Eau de Toilette Spray 100ml","ts":1776573362146},"6151010076081":{"naam":"Luxe Adventskalender Kerstbal","ts":1776573362346},"8719214758523":{"naam":"NG Dominatio men set edp 100 ml + shower gel 50 ml + after shave 50 ml","ts":1776573362568},"8715658002789":{"naam":"Real Time - Red Canyon - Eau De Toilette - 100ML","ts":1776573362760},"8721055490234":{"naam":"Sentio Mary Davina Eau de Parfum Spray 100 ml","ts":1776573362953},"6291012871410":{"naam":"Creation Lamis Just Perfect Dream Giftset","ts":1776573363143},"8721055493167":{"naam":"Hello Kitty-Cotton Candy Scent-15ml Eau de Parfum","ts":1776573363353},"8721055492146":{"naam":"Sentio Chalize for Woman giftset geuren 3x 15ml soorten eau de parfum","ts":1776573363545},"8721055493969":{"naam":"Bubble Bliss - Fantastic Flamingo - Pretty in Pink - Eau de Parfum - Voor Kinderen 15ml","ts":1776573363738},"8721055493914":{"naam":"Bubble Bliss Fantastic Flamingo - Parfum Set Van 6 Stuks - Eau de Parfum Voor Kinderen - 6x15ml","ts":1776575707867},"8715658401636":{"naam":"Linn Young - OSO Perfect Exalted - Eau De Parfum - 100ML for women","ts":1776573363930},"8715658999195":{"naam":"Linn Young Mixed Emotions parfum - Eau de parfum voor dames - 100ML","ts":1776573364137},"7640158816875":{"naam":"Hello Kitty Delicate Flower Eau de Parfum voor Kinderen 50ml","ts":1776573129968},"8715658360018":{"naam":"Real Time - Journee Joyeuse - Eau De Parfum - 100ML","ts":1776573364328},"7640158817018":{"naam":"Hello Kitty - Giftset - Sweet Leopard - Showergel + Eau de Parfum - Cadeauset voor Kinderen - Geschenkset","ts":1776573364536},"8721055493297":{"naam":"Hello Kitty Rainbow Eau de Parfum voor Kinderen 50ml","ts":1776573364728},"7640158816974":{"naam":"Hello Kitty - Giftset - Unicorn Cloud - Showergel + Water-Based Parfum - Cadeauset voor Kinderen - Geschenkset","ts":1776573364934},"8721055493051":{"naam":"Sentio Feestdagen 2 May Your Days be Merry & Bright - Eau de Parfum in kerstbal - 30ml","ts":1776573365152},"8715658013020":{"naam":"Street Looks - La Creation Pour Femme - Eau De Parfum - 100ML","ts":1776573365347},"8719214757489":{"naam":"NG Spectre Fragrances Bruyant For Men eau de toilette 100ml","ts":1776573365547},"8715658330004":{"naam":"Street Looks - Wild Challenge - Eau De Toilette - 100ML","ts":1776573365746},"7640158819227":{"naam":"Vibezz-Violet Journey-Eau de Parfum For Her-100ml","ts":1776573365933},"8715658401681":{"naam":"Linn Young - Admiration Eternal L'originale - Eau de parfum - 100ML","ts":1776573366123},"6291012006003":{"naam":"Creation Lamis Silver Elegance Eau de Toilette 100ml for men","ts":1776573366325},"8715658410102":{"naam":"Georges Mezotti-Black Track For Men Eau de Toilette Spray 100ml","ts":1776573366515},"8719214750749":{"naam":"NG-Bella Vida- Eau de Parfum For Women 15ml","ts":1776573366714},"8719214757403":{"naam":"NG Spectre Fragrances INHUMANE for her eau de parfum 100ml","ts":1776573366913},"6291012005082":{"naam":"Creation Lamis Paraverse 100ml Eau de Parfum for women","ts":1776573367108},"8719214756536":{"naam":"TBY - To Be Edgy - 100ml Eau de Parfum voor vrouwen","ts":1776573367310},"8715658350408":{"naam":"Real Time - Tierra Del Fuego - Eau de toilette - 100ML","ts":1776573367903},"8715658340287":{"naam":"Street Looks Miss Important Eau de Parfum 100ml","ts":1776573368094},"8715658380818":{"naam":"Omerta Lovely Sky - Eau de parfum - 100ML","ts":1776573368289},"6096036236289":{"naam":"Real Time | Eau de parfum | Coup D'amour |Dames","ts":1776573368483},"6291012005464":{"naam":"Creation Lamis Midnight Leather Eau de Toilette 100ml for men","ts":1776573368689},"6291012873902":{"naam":"Dorall Miss Fine damesparfum eau de toilette 90 ml","ts":1776573368891},"8721055493204":{"naam":"Hello Kitty-Little Rose-15ml Eau de Parfum","ts":1776573369083},"8715658370208":{"naam":"Omerta Power Boost For Men Eau de Toilette Spray 100ml","ts":1776573369292},"8715658370666":{"naam":"Omerta - The Winner Takes It All Elixir Absolu - 100ml Eau de Toilette for men","ts":1776573369494},"8721055492405":{"naam":"Vibezz-Botany Grace-Eau de Parfum For Her-100ml","ts":1776573369698},"7640158816011":{"naam":"Sentio Blomicci Vert miniparfum eau de parfum for woman 15ml","ts":1776573369897},"7640158818848":{"naam":"Sentio Paradise Miniparfum Bora Bora Beach eau de parfum for women 15 ml","ts":1776573370121},"8721055494249":{"naam":"Bubble Bliss - Like a Fairytale - Enchanting Eve - Eau de Parfum - Prinsessen Voor Kinderen 15ml","ts":1776573370318},"6151009093075":{"naam":"Next Generation Femme Brilliant for Women edp 100ml","ts":1776573370516},"7640158817865":{"naam":"Sentio Stay Wild Reckless miniparfum eau de parfum for woman 15ml","ts":1776573370738},"8715658370574":{"naam":"Omerta - Red Class Elixir de Luxe - Eau De Parfum - 100ML","ts":1776573370936},"8715658370512":{"naam":"Omerta - L'uomo X Extereme - Eau De Toilette - 100ML","ts":1776573371168},"6291012871069":{"naam":"Creation Lamis Ruler Oud Eau de Toilette 100ml for men","ts":1776573371366},"8719214757441":{"naam":"NG Spectre Fragrances Vili Belo for her eau de parfum 100ml","ts":1776573371561},"8721055493235":{"naam":"Hello Kitty-World Cutest-15ml Eau de Parfum","ts":1776573371764},"8715658012993":{"naam":"Street Looks - City Hopper - Eau De Toilette - 100ML","ts":1776573371962},"8719214757533":{"naam":"NG Spectre Fragrances Le Bucheron For Men eau de toilette 100ml (in plastic fles)","ts":1776573372161},"8715658390756":{"naam":"Linn Young - Pure Luck Elixer Eau De Toilette 100ML","ts":1776573420205},"8715658401759":{"naam":"Linn Young - Oud Elixir d'Extase Satin Whisper - Eau de parfum - 100ML","ts":1776573420397},"7640158819234":{"naam":"Vibezz-French Marine-Eau de Toilette For Him-100ml","ts":1776573420593},"8715658410164":{"naam":"Georges Mezotti-Blue Rain For Men Le Parfum 125ml","ts":1776573420789},"8715658420057":{"naam":"Georges Mezotti Black Intense Eau de parfum 100ml","ts":1776573420999},"8721055492740":{"naam":"SENTIO FEESTDAGEN PINK - Family Magical - Eau de Parfum 50ml","ts":1776573421197},"8715658340263":{"naam":"Street Looks Sensual Goddess Eau de parfum for women 100ml","ts":1776573421416},"6151028285222":{"naam":"NG Home Perfume Predator Spray - 200ml","ts":1776573421599},"7640158815755":{"naam":"Sentio Chalize Geschenkset - 1 set","ts":1776573421798},"8718421831432":{"naam":"Next Generation Boom!! Eau de Parfum 100 ml for women","ts":1776573421995},"6151029223223":{"naam":"Green Nature Aloe Vera pakket 7st.","ts":1776573422189},"7640158817032":{"naam":"Hello Kitty Giftset 3 x 15ml Eau de Parfum","ts":1776573422381},"5145200059016":{"naam":"Omerta La Donna X Eau De Parfum voor haar 100ML","ts":1776573422584},"8715658410133":{"naam":"Georges Mezotti-Brown Track For Men Eau de Toilette Spray 100ml","ts":1776573422781},"8721055493143":{"naam":"Hello Kitty-Banana Scent-15ml Eau de Parfum","ts":1776573422975},"7640158816318":{"naam":"Sentio Big Kisses XOXO parfum - Eau de parfum voor vrouwen - 15ml","ts":1776573423177},"7640158816097":{"naam":"Sentio Ex Plode Elixer eau de parfum Miniparfum for women 15 ml","ts":1776573423370},"7640158815168":{"naam":"Sentio Da Lago eau de parfum miniparfum 15 ml","ts":1776573423566},"7640158816400":{"naam":"Sentio Crevo Eau de Toilette - 100 ml","ts":1776573423752},"8718421830015":{"naam":"NG - BLUE EGAN - 100ml Eau de Toilette for Men","ts":1776573423948},"8721055492658":{"naam":"SENTIO Merry Christmas And Happy New Year Eau de Parfum 15 ml - Miniparfum - Kerst Parfum - Kerst Cadeau - Frisse Geur - Warm - Frissig","ts":1776573424142},"8719214754792":{"naam":"MEEKA Shower Foam Pure Gold 225ml","ts":1776573424337},"8715658401506":{"naam":"Linn Young - Tuscan Sun Unisex - Eau de Parfum 100ml","ts":1776573424526},"6151027884877":{"naam":"NG Home Perfume Dominatio 200ml Spray","ts":1776573424725},"8715658390077":{"naam":"Linn Young - Dangerzone Noir - Eau De Parfum - 100ML","ts":1776573424916},"8715658008354":{"naam":"Real Time - Black Rose - Eau de parfum - 100ML","ts":1776573072344},"8715658401476":{"naam":"Linn Young - Intense Nights Unisex - Eau de Parfum 100ml","ts":1776573425122},"6013902726750":{"naam":"NG-Golddigger-Eau de Toilette For Men 15ml","ts":1776573425324},"6291012873070":{"naam":"Oriental Oud Al Hayat Eau de Toilette 100ml","ts":1776573425854},"6151028770735":{"naam":"NG Home Perfume Crystal Pink 200ml Spray","ts":1776573426056},"7640158817513":{"naam":"Sentio Floricci Eau De Parfum - 100 ml","ts":1776573426248},"7640158819241":{"naam":"Vibezz Il Capitano - Eau de Toilette voor heren - 100ml","ts":1776573127210},"6291012005983":{"naam":"Creation Lamis Identity Spirit Eau de Toilette 100ml for men","ts":1776573426441},"8715658390763":{"naam":"Linn Young - Outer Space for men - Eau De Toilette - 100ML","ts":1776573426717},"8715658400882":{"naam":"Linn Young - The One Beyond - Eau de toilette - 100ML","ts":1776573426921},"7640158816271":{"naam":"Sentio Oud Wood Eau de Toilette - 100 ml","ts":1776573427116},"8715658360520":{"naam":"Real Time Club Classe 100ml","ts":1776573427322},"6013906086096":{"naam":"Green Nature Aloe Vera pakket 6st.","ts":1776573427515},"8715658340270":{"naam":"Street Looks Uptown Babe eau de parfum 100ml","ts":1776573427724},"8715658008576":{"naam":"Real Time - Sexy Dentelle For Woman - Eau de parfum - 100ML","ts":1776573427925},"8719214756031":{"naam":"Homme for men 15ml EDT by NG","ts":1776575765147},"8719214754594":{"naam":"Roomspray Predator by NG 200ml","ts":1776573428131},"6151029165127":{"naam":"NG Home Perfume - Crystal Pink - Set van 3st","ts":1776573428326},"8715658361640":{"naam":"Real Time Style & Class 100ml Eau de Parfum Pour Femme","ts":1776573428542},"8715658002567":{"naam":"Real Time Joyus Eau de parfum - 100 ml","ts":1776573428734},"8718421831586":{"naam":"NG Dominatius Dames Eau de Parfum 100ml","ts":1776573428924},"6013913572544":{"naam":"Green Nature Aloe Vera set van 5st.","ts":1776573429130},"8721055494508":{"naam":"Sentio Strawberry Fusion eau de parfum unisex 15 ml","ts":1776573429329},"7640158817780":{"naam":"Sentio Wishing You The Best miniparfum eau de parfum for woman 15ml","ts":1776573429546},"8715658012955":{"naam":"Street Looks - Black Passion - Eau De Parfum - 100Ml","ts":1776573429757},"8719214756581":{"naam":"TBY - To Be Young - 100ml Eau de Parfum voor vrouwen","ts":1776573429958},"8719214756024":{"naam":"NG Next Fragrance eau de parfum miniparfum for women 15ml","ts":1776573430152},"6291012905818":{"naam":"Dorall -Manipulare- Eau de Toilette for men 100ml","ts":1776573430370},"7640158815960":{"naam":"Sentio Blomicci Azure miniparfum eau de parfum for woman 15ml","ts":1776575593981},"7640158817483":{"naam":"SENTIO All I Want For Is XMAS Is You! Eau de Parfum - Miniparfum 15 ml - Houtachtige Geur - Cacao geur - Vanille - Tabak Geur","ts":1776575594188},"7640158815120":{"naam":"Sentio Inter Feer Eau de Parfum For Women 15ml","ts":1776575594387},"7640158816134":{"naam":"Sentio Best Mom Ever parfum - Cadeau idee voor women eau de parfum - 15ml","ts":1776575594586},"8721055491866":{"naam":"Sentio Arlo Di Hombre Eau de Toilette Spray 100 ml","ts":1776575594803},"8719214757038":{"naam":"NG - HE IS HERE - 100ml Eau de Toilette for Men","ts":1776575595021},"6291012001244":{"naam":"Dorall -Extreme Leather- Eau de Toilette Unisex 95ml","ts":1776575595229},"7640158818787":{"naam":"Sentio Miniparfum Cocktail - ESPRESSO MARTINI - Eau de parfum For Her 15ml","ts":1776575595428},"8715658999027":{"naam":"Omerta - Express sensualite Captive - Eau De Toilette - 100ML","ts":1776575595635},"6291012877818":{"naam":"Dorall -Isle Of Love- Eau de Toilette spray 100ml for women","ts":1776575595843},"8719214753238":{"naam":"NG Mrs. Perfect Giftset","ts":1776575596053},"8721055491767":{"naam":"Sentio Sway With Me Eau de Parfum For Her 50ml","ts":1776575596250},"8721055492108":{"naam":"Sentio - Floricci Geschenkset - 100ml Eau de Parfum + 150ml Showergel","ts":1776575596465},"7640158818831":{"naam":"Sentio Paradise Miniparfum Miami Nights eau de parfum for women 15 ml","ts":1776575596682},"8719214756505":{"naam":"TBY - To Be Strong - 100ml Eau de Toilette voor mannen","ts":1776575596888},"8715658997795":{"naam":"Omerta - Beautiful Pink - Eau De Parfum - 100ML","ts":1776573073557},"8715658380245":{"naam":"Omerta Oh My Dear L'extase parfum - Eau de parfum - 100ML","ts":1776575597097},"8719214750848":{"naam":"NG Wild Men for men eau de toilette 15 ml","ts":1776575597298},"8715658999911":{"naam":"Linn Young - Papillon D'amour - Eau De Parfum - 100ML","ts":1776575597502},"7640158817445":{"naam":"SENTIO Merry Christmas Eau De Parfum 15 ML - Miniparfum - Kerst Parfum - Bloemig - Fruitig","ts":1776575764736},"8715658400134":{"naam":"Linn Young - Gold Mine La Seduction - Eau de parfum - 100","ts":1776575597716},"8721055493938":{"naam":"Bubble Bliss - Fantastic Flamingo - Winging It - Eau de Parfum - Voor Kinderen 15ml","ts":1776575597926},"7640158818756":{"naam":"Sentio Miniparfum Cocktail - TEQUILA SUNRISE - Eau de parfum For Her 15ml","ts":1776575598125},"8719214754167":{"naam":"Next Generation - Eau de Parfum - 15ml - Femme L’Odeur du NG Women","ts":1776575598334},"8715658420132":{"naam":"Georges Mezotti - Queen of Temptation Passion - Eau de parfum 100ml","ts":1776575598533},"7640158818824":{"naam":"Sentio Paradise Miniparfum Ibiza Vibes eau de parfum for women 15 ml","ts":1776575598746},"8715658400899":{"naam":"Linn Young - Club 420 City - Eau de Parfum - 100ML","ts":1776575598947},"7640158818770":{"naam":"Sentio Miniparfum Cocktail - COSMOPOLITAN - Eau de parfum For Her 15ml","ts":1776575599157},"8721055492672":{"naam":"SENTIO May Your Days be Merry & Bright Eau de Parfum 15 Ml - Miniparfum - Zoete geur - Bloemig - Geluk - Cadeau","ts":1776575599361},"8719214750787":{"naam":"NG-DOMINATIO-Eau de Toilette For Men 15ml","ts":1776575599578},"6291012905696":{"naam":"Dorall -King Lucent- Eau de Toilette for men 100ml","ts":1776575599787},"8721055492733":{"naam":"SENTIO FEESTDAGEN PINK - Wonderful - Eau de Parfum 50ml","ts":1776573128780},"8721055490685":{"naam":"Sentio Floricci Rosa miniparfum eau de parfum 15ml","ts":1776575599994},"8715658969600":{"naam":"Linn Young - OSO No Guts No Glory - Eau De Toilette - 100ML","ts":1776575600199},"7640158814888":{"naam":"Sentio Da Lago Eau De Parfum - 100 ml","ts":1776575600606},"8719214750954":{"naam":"NG Caught Men Eau de Toilette Spray 100 ml","ts":1776573125402},"7640158815731":{"naam":"Sentio Ciro di Hombre Eau de Toilette - 100 ml","ts":1776575600809},"8719214756567":{"naam":"TBY - To Be Sparkling - 100ml Eau de Parfum voor vrouwen","ts":1776575601013},"8715658401292":{"naam":"Linn Young - Outerspace Reborn Women - Eau de parfum - 100ML","ts":1776575601217},"7640158818794":{"naam":"Sentio Miniparfum Cocktail - MOJITO - Eau de parfum For Her 15ml","ts":1776575601427},"7640158816929":{"naam":"Hello Kitty Unicorn Parfum set 6 stuks voor kinderen - 6x15ml - Meisjes","ts":1776575601682},"7640158815977":{"naam":"Sentio Blomicci Poudre miniparfum eau de parfum for woman 15ml","ts":1776575601908},"8715658350279":{"naam":"Real Time - Pure On The Rocks For Men - Eau De Toilette - 100ML","ts":1776575602127},"8715658998570":{"naam":"Linn Young - Homerun Prestige - Eau De Toilette - 100ML","ts":1776575602329},"7640158817773":{"naam":"Sentio Thinking Of You! miniparfum eau de parfum for woman 15ml","ts":1776575602533},"8721055493273":{"naam":"Hello Kitty Kisses Eau de Parfum voor Kinderen 50ml","ts":1776573186805},"8715658401117":{"naam":"Linn Young - Techno Tronics Woman - Eau de parfum - 100ML","ts":1776575602764},"8719214757359":{"naam":"NG Spectre Fragrances Cerulean Blue for her eau de parfum 100ml","ts":1776575602967},"8715658400172":{"naam":"Linn Young - Mystery & Excellence Eau De Parfum 100ML","ts":1776575603183},"8721055494324":{"naam":"Bubble Bliss Parfum Giftbag Glimmering Grace EDP voor meisjes 50ml","ts":1776573073143},"8715658998679":{"naam":"Linn Young - Homerun Sports - Eau De Toilette - 100ML","ts":1776575603397},"8715658370420":{"naam":"Omerta -Meet Me Extreme- 100ml Eau de Toilette for men","ts":1776575603612},"8715658390534":{"naam":"Linn Young Mighty Mood Men Giftset Eau de Toilette 100ml + 30ml","ts":1776575603840},"8721055490364":{"naam":"Sentio - mini parfum - Lucky Numbers 4 Four Ever - eau de parfum - 15ml","ts":1776575604051},"0764158815106":{"naam":"Sentio Suffix woman edp 15ml","ts":1776575604299},"8715658013075":{"naam":"Street Looks - Oh La Chicca - Eau de parfum - 100 ml","ts":1776575641355},"8721055494546":{"naam":"Sentio Peachy Paradise eau de parfum unisex 15 ml","ts":1776575641556},"8715658370147":{"naam":"Omerta Liquid Marble Eau de Toilette 100ml","ts":1776575641764},"7640158815281":{"naam":"Sentio Gold Fever Mini tasverstuiver homme 15ml edt","ts":1776575641964},"8715658401063":{"naam":"Linn Young - Blue 4 You - Eau de parfum - 100ML","ts":1776575642161},"4042342003024":{"naam":"HOT SHIATSU Pheromone Perfume - Voor mannen - 15 ml","ts":1776575642359},"5414666011877":{"naam":"Dorall Fluid Intense - Houtachtig aromatische eau de toilette voor mannen - 100ml","ts":1776575642568},"8715658997924":{"naam":"Omerta - Fair Fight - Eau De Toilette - 100Ml","ts":1776575642767},"7640158815984":{"naam":"Sentio Blomicci Blanche miniparfum eau de parfum for woman 15ml","ts":1776575642966},"8721055492795":{"naam":"Sentio What Happens Under The Mistletoe Stays Under The Mistletoe - Eau de parfum","ts":1776575643181},"8721055493082":{"naam":"SENTIO FEESTDAGEN PINK - Happy Holidays - Body Mist 250ml","ts":1776575643581},"8719214750237":{"naam":"NG - Burnt Vanilla - Eau de Parfum 100ml","ts":1776575643386},"8715658350118":{"naam":"Real Time - No Ordinary - Eau de toilette - 100ML","ts":1776575643788},"7640158814826":{"naam":"Sentio Suffix Eau De Parfum - 100 ml","ts":1776575643992},"8719214757434":{"naam":"NG Spectre Fragrances Noré for her eau de parfum 100ml","ts":1776575644192},"8721055492757":{"naam":"SENTIO FEESTDAGEN - Kerst Giftset Christmas Tree - Merry Christmas","ts":1776575644398},"8721055493464":{"naam":"Hello Kitty - Giftset - Mermaid Pink - Showergel + Eau de Parfum - Cadeauset voor Kinderen - Geschenkset","ts":1776575644608},"6291012884946":{"naam":"Creation Lamis Classy Love Eau de Parfum for women 100ml","ts":1776575644807},"7640158817889":{"naam":"Sentio Stay Wild Wildfire miniparfum eau de parfum for woman 15ml","ts":1776575645014},"5020353054234":{"naam":"Oriental Al Oud Al Safi Eau de Toilette 100ml","ts":1776575645219},"7640158817216":{"naam":"Sentio Giftset-Blomicci-Parfum en Showergel","ts":1776575645421},"7640158815779":{"naam":"Sentio Patron Geschenkset - 1 set","ts":1776659171592},"8719214757465":{"naam":"NG Spectre Fragrances Blue Onyx For Men eau de toilette 100ml","ts":1776575645619},"8715658360209":{"naam":"Real Time - Spartanian Lady - Eau De Parfum - 100ML","ts":1776575645823},"8721055499473":{"naam":"Sentio Love Van Love & Casual Eau de Parfum 100 ml","ts":1776575646076},"7640158815182":{"naam":"Sentio Confirmation Eau de Parfum For Women 15ml","ts":1776575646281},"8715658012948":{"naam":"Street Looks - Amour Fatale - Eau De Parfum - 100ML","ts":1776575646483},"8715658400240":{"naam":"Linn Young - Mixed Emotions Sparkling Pour Femme - Eau De Parfum - 100ML","ts":1776575646723},"8721055490487":{"naam":"Sentio - mini parfum - You Are My Hero - heren - vaderdag - eau de toilette - 15 ml","ts":1776575646927},"7640158819173":{"naam":"Vibezz Astrolux parfum - Eau de parfum voor haar - 100ml","ts":1776575647134},"7640158816424":{"naam":"Sentio Bella Strada Eau De Parfum - 100 ml","ts":1776575647338},"8715658400387":{"naam":"Linn Young Coeur Pure parfum - Eau de parfum - 100ml","ts":1776575647540},"8721055494041":{"naam":"Bubble Bliss - Giftset - Unicorn Dreamy Glitterwings - Showergel + Eau de Parfum - Cadeauset voor Kinderen - Geschenkset","ts":1776575647747},"5414666009485":{"naam":"Creation Lamis - Golden Wave for him - Eau de Toilette 100ml","ts":1776575647956},"7640158817407":{"naam":"Sentio Rojo Eau De Parfum - 100 ml","ts":1776575648175},"7640158816851":{"naam":"Hello Kitty Graffiti parfum - Eau de parfum voor kinderen - 50 ml","ts":1776573123992},"8721055496984":{"naam":"De La Mare Cookies parfum - Koekjes Geur voor vrouwen eau de parfum - 15 ml","ts":1776573184817},"8719214757502":{"naam":"NG Spectre Fragrances Excelsus MEN For Men eau de toilette 100ml","ts":1776575648374},"7640158818862":{"naam":"Sentio Paradise Miniparfum Rio Rhythm eau de parfum for women 15 ml","ts":1776575648575},"8719214754556":{"naam":"Next Generation Predator Roomsticks 200ml","ts":1776573183212},"8719214757496":{"naam":"NG Spectre Fragrances Cheff For Men eau de toilette 100ml","ts":1776575648775},"7640158819210":{"naam":"Vibezz-Mythic Woman-Eau de Parfum For Her-100ml","ts":1776575648993},"8715658361428":{"naam":"Real Time - Morning Bloom - Eau De Parfum - 100ML","ts":1776575649194},"8715658969662":{"naam":"Georges Mezotti Base Track High Society - Eau de Toilette - 100 ml","ts":1776575649397},"7640158816042":{"naam":"Sentio Ex Plode Fusion eau de parfum Miniparfum for women 15 ml","ts":1776575649612},"7640158816059":{"naam":"Sentio Ex Plode Crush eau de parfum Miniparfum for women 15 ml","ts":1776575649815},"8715658360698":{"naam":"Real Time - Fine Gold For Women - Eau de parfum - 100ML","ts":1776575650018},"7640158817810":{"naam":"Sentio Let The Party Begin miniparfum eau de parfum for unisex 15ml","ts":1776575650236},"8715658999447":{"naam":"Omerta - Vanilla Fun - Eau De Parfum - 100ML","ts":1776573185058},"8715658013082":{"naam":"Street Looks - Pure Courage - Eau de Toilette - 100ML","ts":1776573067754},"6291012005648":{"naam":"Creation Lamis My Spirit Eau de Parfum For Women 100ml","ts":1776575600405},"8721055492344":{"naam":"Vibezz-Sagini-Eau de Toilette For Him-100ml","ts":1776575650436},"7640158816530":{"naam":"Sentio Zodiac - Virgo - Maagd - Eau De Parfum - For Women - 15ml","ts":1776575650644},"7640158816547":{"naam":"Sentio Zodiac - Libra - Weegschaal - Eau De Parfum - For Women - 15ml","ts":1776575651051},"7640158816561":{"naam":"Sentio Zodiac - Sagitarius - Boogschutter - Eau De Parfum - For Women - 15ml","ts":1776575651506},"6151009790714":{"naam":"Luxe Adventskalender Kerstboom","ts":1776575701558},"8715658360063":{"naam":"Real Time Coup d'Amour eau de parfum 100 ml.","ts":1776575701781},"7640158816493":{"naam":"Sentio Zodiac - Taurus - Stier - Eau De Parfum - For Women - 15ml","ts":1776575702001},"8719214759667":{"naam":"NG Perfume Stick - DARK CHERRY - 10gr","ts":1776575702219},"8719214759650":{"naam":"NG Perfume Stick - BELLA VIDA - 10gr","ts":1776575702417},"6151028564525":{"naam":"NG Home Perfume Dominatio - Geurstokjes, Refill & Roomspray set van 3","ts":1776575702615},"7640158816523":{"naam":"Sentio Zodiac - Leo - Leeuw - Eau De Parfum - For Women - 15ml","ts":1776575702822},"6291012005099":{"naam":"Creation Lamis Paraverse Giftset for her","ts":1776575703026},"5414666016216":{"naam":"Dorall Lancy parfum Eau de Toilette voor haar - Zwarte bes, Peer, Iris - 100ml","ts":1776575703224},"6013914322353":{"naam":"Sentio Living Legend Men Eau de Toilette 3stuks x 100ml","ts":1776575703626},"8719214759193":{"naam":"NG Delusional for her miniparfum eau de parfum 15ml","ts":1776573076335},"8719214750060":{"naam":"NG Golddigger parfum voor men - Eau de Toilette met kruidige noten - 100ml + 15ml","ts":1776575764537},"8715658360995":{"naam":"Real Time - Smart Lady For Women - Eau de parfum - 100ML","ts":1776575703834},"6013905032025":{"naam":"Creation Lamis - Arrivederci - 100 ml - Eau de Toilette - Herenparfum","ts":1776575704234},"6151010029070":{"naam":"Creation Lamis Catsuit Woman Eau de Parfum For Women 100 ml","ts":1776575704431},"8719214750121":{"naam":"HORUS - Egyptian Powder - Bronzer - 17gr","ts":1776575704643},"7640158816578":{"naam":"Sentio Zodiac - Capricorn - Steenbok - Eau De Parfum - For Women - 15ml","ts":1776575704859},"8719214753641":{"naam":"NG - Phenom - Eau de Parfum 100ml voor dames","ts":1776575705069},"6151009090036":{"naam":"NG Crystal Pink Eau de Parfum 100 ml","ts":1776575705573},"8715658360049":{"naam":"REAL TIME Love You Pink EDP 100ml","ts":1776575705782},"8715658361671":{"naam":"Real Time Roman Empire Women Velluto Rosa parfum - Eau de parfum voor dames - 100ml","ts":1776575705988},"8719214759551":{"naam":"NG Woody Soul Unisex eau de parfum 100ml","ts":1776575706193},"8719214751203":{"naam":"NG Classic Men Eau de Toilette Spray 100 ml","ts":1776573071559},"8715658401599":{"naam":"Linn Young Admiration Eternal Intenso Eau de Parfum 100ml","ts":1776575706431},"8721055499282":{"naam":"Sentio Casual Van Love & Casual Eau de Parfum 100 ml","ts":1776575706643},"7640158816516":{"naam":"Sentio Zodiac - Cancer - Kreeft - Eau De Parfum - For Women - 15ml","ts":1776575706842},"7640158815007":{"naam":"Sentio Gold Fever Eau de Toilette - 100 ml","ts":1776575707041},"7640158816592":{"naam":"Sentio Zodiac - Pisces - Vissen - Eau De Parfum - For Women - 15ml","ts":1776575707245},"8721055491477":{"naam":"Sentio Vintage Forrest Unisex Eau de Parfum 100ml","ts":1776575707668},"8721055494126":{"naam":"Sentio I Love You Giftset","ts":1776575708065},"8721055491354":{"naam":"Sentio Opal Glow Unisex Eau de Parfum 100ml","ts":1776575708271},"8718421830695":{"naam":"NG Home - DARK CHERRY - Geurkaars 180gr","ts":1776575708687},"8718421831579":{"naam":"NG Bella Vida Eau de Parfum 80 ml","ts":1776575711790},"8719214750107":{"naam":"NG Bella Vida Eau de Parfum 80 ml + 15ml","ts":1776575708885},"7640158816370":{"naam":"Sentio Blossoms of Joy Exotic miniparfum eau de parfum 15 ml","ts":1776575709101},"8721055492955":{"naam":"Luxe Adventskalender Groen met 24 mini Flesjes Eau de Parfum","ts":1776575709314},"8718421830671":{"naam":"NG Home - PREDATOR - Geurkaars 180gr","ts":1776575709514},"8715658361473":{"naam":"Real Time - Queen Of Space Glorious - Eau De Parfum - 100ML","ts":1776575709720},"8721055490524":{"naam":"Sentio - mini parfum - Best Friend Ever - heren - vaderdag - eau de toilette - 15 ml","ts":1776575709918},"8720938379284":{"naam":"Omerta - Night Power Pack - set van 3x100ml","ts":1776575710129},"8718421830688":{"naam":"NG Home - DOMINATIO - Geurkaars 180gr","ts":1776575710535},"8715658361466":{"naam":"Real Time - Oú sont les - Eau de parfum - 100 ml","ts":1776573122150},"8715658400745":{"naam":"Linn Young -Dryade Giftset- Eau de parfum 100ml + 30ml","ts":1776575710963},"8715658360896":{"naam":"Real Time Queen of Space parfum - Eau de parfum voor elegante vrouwen - 100ml","ts":1776575711159},"8715658350620":{"naam":"Real Time Cops For Men 2.0 - Eau de Toilette voor heren - 100ML","ts":1776575711363},"8715658350637":{"naam":"Real Time Wild Action Elixir men edt 100 ml","ts":1776575711569},"8715658007036":{"naam":"Real Time - Miss Sexy - Pour Femme Eau de Parfum 100ml","ts":1776575761959},"6151029325385":{"naam":"NG - Predator - 100ml Eau de Parfum voor dames +Tas verstuiver","ts":1776575762177},"8719214758561":{"naam":"NG - Aqua Di NG - Eau de Toilette 100ml","ts":1776575762413},"8715658998419":{"naam":"Omerta Pommy & Passion Eau de Parfum 100ml","ts":1776575762615},"8721055490326":{"naam":"Parfum SENTIO Lucky Numbers 8 Great Eight eau de parfum 15ml","ts":1776575762827},"6291012905375":{"naam":"Dorall -DC Empress- Eau de Toilette spray 100ml for women","ts":1776575763026},"8715658350361":{"naam":"Real Time - Intense Impression For Men - Eau De Toilette - 100ML","ts":1776575763251},"8715658002796":{"naam":"Real Time Canyon night 100 ml eau de toilette spray","ts":1776575763458},"8715658350354":{"naam":"Real Time Challenging Life Eau de Toilette 100ml","ts":1776575763725},"8715658410126":{"naam":"Georges Mezotti-Red Track For Men Eau de Toilette Spray 100ml","ts":1776575763929},"8715658401483":{"naam":"Linn Young - Tobacco & Vanilla Unisex - Eau de Parfum 100ml","ts":1776575764328},"8721055492641":{"naam":"SENTIO Happy Holidays Eau de Parfum 15 ml - Miniparfum - Kerst parfum - Kerst Cadeau - Fris - Feestdagen","ts":1776575765779},"8721055497004":{"naam":"De La Mare Straccia - Stracciatella Geur - For Women Eau de Parfum 15 ml","ts":1776575765996},"8719214750138":{"naam":"HORUS - Egyptian Powder - Grote verpakking - 40gr","ts":1776575766201},"8715658361619":{"naam":"Real Time - Tempting Rumors - Eau de Parfum 100ml","ts":1776575766407},"8715658002772":{"naam":"Real Time - Night Blue Mission Pour Homme - Eau De Toilette - 100ML","ts":1776575766613},"8715658002734":{"naam":"Real Time - Life In Motion For Women - Eau de parfum - 100ML","ts":1776575766817},"6291012875173":{"naam":"Dorall -Golden Blaze- Eau de Parfum 100ml","ts":1776575767040},"8715658008699":{"naam":"Real Time Acqua Di Mare Eau de Parfum 100ml","ts":1776575767272},"8721055493723":{"naam":"Sentio Love & Casual for Him Eau de Toilette Spray 100 ml","ts":1776575767474},"8715658401285":{"naam":"Linn Young - Outerspace Invasion - Eau de parfum - 100ML","ts":1776575767682},"8715658401230":{"naam":"Linn Young - Oud Elixir d'Extase Gold Label - Eau de parfum - 100ML","ts":1776575767885},"8715658390527":{"naam":"Linn Young -Techno Tronics- 100ml EDT","ts":1776575768108},"8715658350125":{"naam":"Real Time - Ad Vitam Aeternam - Eau De Toilette - 100ML","ts":1776575768324},"8721055493129":{"naam":"Hello Kitty-Strawberry Scent-15ml Eau de Parfum","ts":1776575768526},"7806139167118":{"naam":"Aroma olie - Fragrance Oil 'Exotic Lychee' - 750 ml - Geurolie voor oliebranders","ts":1776575768729},"8721055493488":{"naam":"Hello Kitty - Giftset - Mermaid Mint - Showergel + Eau de Parfum - Cadeauset voor Kinderen - Geschenkset","ts":1776575768931},"8720938379253":{"naam":"Colorful Shoe Shoe Pack","ts":1776575769159},"8719214753269":{"naam":"Next Generation Classic Woman Elegance Eau de Parfum 100ml","ts":1776575769396},"8715658380023":{"naam":"Omerta - Wild Poppy - Eau De Parfum - 100ML","ts":1776575769607},"8715658350446":{"naam":"Real Time - Blue Touch - Eau De Toilette - 100Ml","ts":1776575769803},"8715658390558":{"naam":"Linn Young - Wild Adventure Absolu - Eau de toilette - 100ML","ts":1776575770034},"6291012899858":{"naam":"Creation Lamis The Great Eau de Toilette 100ml","ts":1776575770269},"8715658400295":{"naam":"Linn Young \"Je Suis Sure Et Certaine\" Eau de parfum 100ml","ts":1776575770486},"6291012005518":{"naam":"Dorall geschenkset Giftset Majestic Sandal 105mledt sh+Body","ts":1776575770698},"7640158816080":{"naam":"Sentio Ex Plode Spark eau de parfum Miniparfum for women 15 ml","ts":1776575770907},"8721055490647":{"naam":"Sentio Floricci Corallo miniparfum eau de parfum 15ml","ts":1776575771113},"8721055495970":{"naam":"SENTIO FEESTDAGEN PINK - Merry Christmas And Happy New Year - Body Mist 250ml","ts":1776575771328},"8715658380801":{"naam":"Omerta - Candy Puff - Eau de parfum - 100ML","ts":1776575771532},"8715658013068":{"naam":"Street Looks Night Time Love - Eau de parfum voor vrouwen - 100 ml","ts":1776575771743},"6291012875814":{"naam":"Dorall Black Light damesparfum - Eau de toilette met vanille noten - 100ml","ts":1776575771962},"8719214751197":{"naam":"NG Eau de Toilette Goldigger Men 100 ml","ts":1776575772186},"6291012004986":{"naam":"Dorall Giftset Miss Fine voor dames","ts":1776575772387},"8715658390367":{"naam":"Linn Young - Work@holics Giftset For Men -","ts":1776575820372},"7640158815229":{"naam":"Sentio DLM Eau de Parfum For Women 15ml","ts":1776575820578},"8719214759162":{"naam":"NG Lightness for Women miniparfum eau de parfum 15ml","ts":1776575820773},"6291012002722":{"naam":"Dorall geschenkset Giftset Dames geur Lancy 110ml edt 210ml","ts":1776575821005},"6013906727746":{"naam":"NG Femme. L'odeur du NG Eau de Parfum 100ml + 15ml","ts":1776575821207},"8721055490340":{"naam":"Parfum SENTIO Lucky Numbers 2 Two Be eau de parfum 15ml","ts":1776575821413},"8715658390008":{"naam":"Admiration Black by Linn Young 100 ml - Eau De Toilette Spray","ts":1776575821614},"8719214757458":{"naam":"NG Spectre Fragrances Your Luxe for her eau de parfum 100ml","ts":1776575821836},"7640158815656":{"naam":"Sentio Blomicci Eau De Parfum - 100 ml","ts":1776575822239},"8715658401308":{"naam":"Linn Young - Outerspace Women - Eau de parfum - 100ML","ts":1776575822439},"6291012005662":{"naam":"Creation Lamis Diva Essence Eau de Parfum For Women 100ml","ts":1776575822649},"8719214757427":{"naam":"NG Spectre Fragrances NARIGUEZ for her eau de parfum 100ml","ts":1776575822866},"8719214757373":{"naam":"NG Spectre Fragrances Floralle for her eau de parfum 100ml","ts":1776575823072},"8719214757526":{"naam":"NG Spectre Fragrances FUNDA MENTALS for him eau de toilette 100ml","ts":1776575823284},"8719214757397":{"naam":"NG Spectre Fragrances GOLD GENERATION for her eau de parfum 100ml","ts":1776575823514},"8715658401032":{"naam":"Linn Young - Admiration Eternal - Eau de parfum - 100ML","ts":1776575823711},"6291012874121":{"naam":"Dorall Love You Like Crazy Eau de Toilette for women 100ml","ts":1776575823912},"8714319228841":{"naam":"Amando Mystery Aftershave - 100 ml","ts":1775966582503},"8721055490661":{"naam":"Sentio Floricci Verde miniparfum eau de parfum 15ml","ts":1776575824119},"8715658013099":{"naam":"Rotsen & Stenen Eau de Toilette Spray 100ml","ts":1776575824328},"8715658420071":{"naam":"Georges Mezotti - You'Re Perfect Love - Eau De Parfum - 100Ml","ts":1776575824530},"8715658390565":{"naam":"Linn Young - Club 420 Switch - Eau de toilette - 100ML","ts":1776575824732},"6151009394318":{"naam":"Next Generation Golden Pearl parfum voor vrouwen - Eau de parfum - 100 ml","ts":1776575824946},"8715658002840":{"naam":"Real Time - Sea Beach - Eau De Toilette - 100ML","ts":1776575825148},"8715658998471":{"naam":"Omerta Body Survival For Man - Eau de Toilette voor heren - 100ML","ts":1776575825352},"8719214751098":{"naam":"Green Nature - Aloe Vera - Voetencreme - Zorgt voor een fris gevoel - Verzorging van gespannen voeten - Droge voeten","ts":1776575825559},"7640158817469":{"naam":"SENTIO What Happens Under The Mistletoe Stays Under The Mistletoe Eau de Parfum - Miniparfum 15 Ml- Houtachtige Geur - Saffraan - Kerst - Kerst Geur","ts":1776575825967},"8715658401254":{"naam":"Linn Young - Breek Free Absolu - Eau de parfum - 100ML","ts":1776575826167},"8721055498445":{"naam":"SENTIO DE LA MARE YAKIRA BODYMIST 250ML CANDY LAND SUGAR DELIGHT/41","ts":1776575826371},"8714319228827":{"naam":"Amando Mystery Eau de Toilette voor mannen - Kruidige vanille parfum - 50 ml","ts":1776575826569},"7438235478432":{"naam":"Next Generation Femme L'Odeur Du NG parfum - Eau de parfum voor dames - 100ml","ts":1776575826778},"7640158816943":{"naam":"Hello Kitty Choose Your Style Parfum set 6 stuks voor kinderen - 6x15ml - Meisjes","ts":1776575826979},"8721055492184":{"naam":"Bubble Bliss Flamingo Giftbook Parfum Pink & Proud EDP voor meisjes 50ml","ts":1776575827180},"8715658390374":{"naam":"Linn Yong Last Frontier Eau de Toilette Spray 100ml","ts":1776575827391},"8721055491439":{"naam":"Sentio Scarlett Fruits Unisex Eau de Parfum 100ml","ts":1776575827594},"8719214759179":{"naam":"NG - Next Generation - Elinné miniparfum eau de parfum 15ml","ts":1776575827795},"8720938379307":{"naam":"Omerta - Oud & Class Pack - set van 3x100ml","ts":1776575827993},"8715658370093":{"naam":"Omerta Big The Fragrance Release - Eau de Toilette - 100ML","ts":1776575828205},"7640158815892":{"naam":"Sentio Blossy Parfum - Eau de parfum voor haar - 35ml","ts":1776575828411},"8721055495765":{"naam":"Atelier Privee Mistical France Unisex - Sugar Fortune - Eau de Parfum - 100ml","ts":1776575828615},"8721055499916":{"naam":"Sentio - TINA - Body Mist 250ml","ts":1776575829021},"8719992723812":{"naam":"Catsuit Man parfum - Heren eau de toilette met munt, lavendel en bergamot","ts":1776575829240},"6151028763713":{"naam":"NG Home Perfume - Predator - Set van 3st","ts":1776575829444},"8715658360643":{"naam":"Real Time - Sweet Caresse For Women - Eau De Parfum - 100ML","ts":1776575829647},"8715658370185":{"naam":"Omerta Accountable Stijle Eau de Toilette 100ml","ts":1776575829846},"8715658420064":{"naam":"Georges Mesotti You're Perfect Darling Eau de Parfum 100ml","ts":1776575830051},"8715658350033":{"naam":"Real Time - Out Of Order - Eau De Toilette - 100ML","ts":1776575830252},"8719214754488":{"naam":"Geurverspreider Vivance aromatische canvas bergamot, lavendel oliën met stokjes 100 ml","ts":1775966588253},"8715658350453":{"naam":"Real Time - Legendary Life For Men - Eau de toilette - 100ML","ts":1776575830471},"8715658012450":{"naam":"Georges Mezotti - Expedition Experience Black Edition - Eau De Toilette - 100ML","ts":1776575880486},"8719214754501":{"naam":"Geurverspreider Vivance Serene Lotus Harmony in bloom met stokjes","ts":1775966588811},"8719214750770":{"naam":"NG-Dominatio-Eau de Parfum For Women 15ml","ts":1776575880692},"7640158814949":{"naam":"Sentio DLM Eau De Parfum - 100 ml","ts":1776575880892},"8715658390015":{"naam":"Admiration Pure by Linn Young 100 ml - Eau De Toilette Spray","ts":1776575881096},"8719214750640":{"naam":"NG Wild Men Eau de Toilette Spray voor heren - Kruidige en frisse geur - 100 ml","ts":1776575881298},"8715658361015":{"naam":"Real Time - Fine Gold Pink Vibrations - Eau de parfum - 100ML","ts":1776575881535},"8715658360124":{"naam":"Real Time - Live & Surprose - Eau de parfum - 100","ts":1776575881734},"8721055493068":{"naam":"Sentio Happy Holidays Pink parfum - Eau de parfum in kerstbal - 30ml","ts":1776573248681},"6291012874428":{"naam":"Dorall Win Over parfum - Eau de Toilette voor haar - 100ml","ts":1776575704036},"8715658360865":{"naam":"Real Time - Queen Of Space Blazing Sky - Eau De Parfum - 100Ml","ts":1776575764128},"8719214754105":{"naam":"MEEKA Ouvert Eau de Parfum - Bloemige geur met lavendel en oranjebloesem - 100ml","ts":1776575765356},"8721055495826":{"naam":"Atelier Privee - Mistical France - VANILLA CHIQUE - Unisex eau de parfum 100ml","ts":1776575822038},"7640158819265":{"naam":"Vibezz-24K-Eau de Toilette For Him-100ml","ts":1776575825762},"8715658350514":{"naam":"Real Time - Call Me Black Edition - Eau de toilette - 100ML","ts":1776575828820},"8719214754563":{"naam":"Next Generation NG Geurstokjes Dominatio - 200ml","ts":1776575881938},"8721349102683":{"naam":"Azira - Black Throne - Eau de Parfum Unisex","ts":1776575882153},"8719214751159":{"naam":"Green Nature - Aloe Vera - Cooling Gel - Verkoelt en verfrist - Zorgt voor een fris gevoel","ts":1776575882354},"8715658400998":{"naam":"Linn Young Danger Zone Noir Giftset Eau de Parfum 100ml + 30ml for women","ts":1776575882574},"8715658380795":{"naam":"Omerta - Patchouli - Eau de parfum - 100ML","ts":1776575882779},"5414666010511":{"naam":"Dorall 24 pure for men eau de toilette herenparfum 100ml","ts":1776575882981},"8721055492207":{"naam":"Bubble Bliss Flamingo Giftbook Parfum You're Flamazing EDP voor meisjes 50ml","ts":1776575883188},"7640158815670":{"naam":"Sentio Sirenic Eau De Parfum - 100 ml","ts":1776575883409},"8715658420163":{"naam":"Georges Mezotti - Queen of Temptation Elegance - Eau de parfum 100ml","ts":1776575883626},"8715658350064":{"naam":"Real Time Submarine Eau de Toilette Spray 100ml","ts":1776575883834},"8719214758349":{"naam":"NG Mrs. Unique parfum - Eau de parfum voor dames - 100ml","ts":1776575884037},"8715658401315":{"naam":"Linn Young -Technotronics Woman Giftset- Eau de parfum 100ml + 30ml","ts":1776575884265},"7640158815991":{"naam":"Sentio Blomicci Noir miniparfum eau de parfum for woman 15ml","ts":1776575884923},"5414666002103":{"naam":"Creation Lamis Temperature Eau de Toilette for men 100ml","ts":1776575885126},"6151027512541":{"naam":"NG Home Next Fragrance Geurstokjes 200ml","ts":1776575885331},"8721055493709":{"naam":"Sentio Love & Casual for Her Eau de Parfum Spray 100 ml","ts":1776575885538},"8721055494065":{"naam":"Bubble Bliss - Giftset - Unicorn Cherry Blossom Fantasy - Showergel + Eau de Parfum - Cadeauset voor Kinderen - Geschenkset","ts":1776575885829},"8715658998563":{"naam":"Omerta - Sweet Pommy - Eau de parfum - 100ML","ts":1776575886031},"8720935400080":{"naam":"Creascents Geurolie Sicilian Bergamot 750 Ml Transparant","ts":1776575886241},"8719214757410":{"naam":"NG Spectre Fragrances UNTOUCHABLE for her eau de parfum 100ml","ts":1776575886478},"7640158814963":{"naam":"Sentio Patron Eau de Toilette - 100 ml","ts":1776575886694},"8719214750961":{"naam":"Next Generation Classic for Woman 100ml Eau de Parfum","ts":1776575886893},"8715658400585":{"naam":"Linn Young -Dryade Paris- Eau de Parfum 100ml","ts":1776575887104},"8715658401223":{"naam":"Linn Young Oud Elixer d 'Extase Pink Label edp 100ml Unisex","ts":1776575887302},"6151029178158":{"naam":"Bubble Bliss - Parfum Set Van 4 Stuks - Eau de Parfum Voor Kinderen - 4x15ml","ts":1776575887516},"6291012001268":{"naam":"Dorall -Majestic Sandal- Eau de Toilette Unisex 95ml","ts":1776575887725},"8715658360988":{"naam":"Real Time - Lapins - Eau De Parfum - 100Ml","ts":1776575887925},"5414666014229":{"naam":"Dorall -DC Marine- Eau de Toilette 100ml","ts":1776575888144},"8715658997764":{"naam":"Omerta - Angelina - Eau De Parfum - 100ML","ts":1776575888358},"8715658997283":{"naam":"Linn Young - Just For Me - Eau de parfum - 100ML","ts":1776575888568},"8715658009733":{"naam":"Real Time Mise Eau de Toilette100ml","ts":1776575888775},"8715658350071":{"naam":"Real Time Submarine Operation X Eau de Toilette 100ml","ts":1776575889218},"8721055496373":{"naam":"Hello Kitty - Giftset - Sweet Leopard Pink - Eau de Parfum + Bodymist - Cadeauset voor Kinderen - Geschenkset","ts":1776575889429},"6291012000261":{"naam":"Creation Lamis Overdrive Eau de Parfum 100ml","ts":1776575889654},"8719214756482":{"naam":"TBY - To Be Awesome - 100ml Eau de Toilette voor vmannen","ts":1776575889861},"8719214756543":{"naam":"TBY - To Be Passionate - 100ml Eau de Parfum voor vrouwen","ts":1776575890062},"8715658410119":{"naam":"Georges Mezotti-Blue Track For Men Eau de Toilette Spray 100ml","ts":1776575890259},"6291012873230":{"naam":"Oriental Ishq Al Ayoon Eau de Toilette 100ml","ts":1776575890468},"8719214758332":{"naam":"NG Routines de L'Homme Eau de Toilette 100ml","ts":1776575890666},"8719214756475":{"naam":"TBY - To Be Active - 100ml Eau de Toilette voor mannen","ts":1776575890870},"8718421831302":{"naam":"NG Secret Code Sport for Men - 100 ml - Eau de Toilette","ts":1776575891071},"8721055492719":{"naam":"SENTIO FEESTDAGEN PINK - Holly Jolly Magic - Eau de Parfum 50ml","ts":1776575891274},"8719214750022":{"naam":"NG DOMINATIO 80ml + 15ml Eau De Toilette","ts":1776575941316},"7640158818121":{"naam":"Sentio Giftset-Crevo Masculine-Eau de Toilette en Showergel","ts":1776575941513},"8721055490654":{"naam":"Sentio Floricci Viola miniparfum eau de parfum 15ml","ts":1776575941721},"8715658009054":{"naam":"Real Time Silenzia For Men - Eau de Toilette voor heren - 100ml","ts":1776575941923},"7640158815205":{"naam":"Sentio Single Lady Eau de Parfum For Women 15ml","ts":1776575942129},"8719214753221":{"naam":"NG Homme for Men Giftset","ts":1776575942333},"7438235478494":{"naam":"NG Dominatio Woman Eau de Parfum - Damesparfum met frisse en elegante geur - 100ml","ts":1776575942542},"6151028518580":{"naam":"NG Home Perfume - Bella Vida - Set van 3st","ts":1776575942742},"8715658370567":{"naam":"Omerta - Conclude Oud Eternal Glory - Eau De Parfum - 100ML","ts":1776575942948},"7640158816899":{"naam":"Hello Kitty Googly Line Eau de Parfum voor Kinderen 50ml","ts":1776575943176},"8719214754150":{"naam":"NG-Crystal Pink-Eau de Parfum for Women 15ml","ts":1776575943375},"8715658420149":{"naam":"Georges Mezotti - Queen of Temptation Fatale - Eau de parfum 100ml","ts":1776575943589},"5414666007801":{"naam":"Creation Lamis Colosseum Eau De Toilette Heren - Oriëntaals houtachtig - 100 ml","ts":1776575943790},"8721055493105":{"naam":"Hello Kitty Mermaid Parfum set 6 stuks voor kinderen - 6x15ml - Meisjes","ts":1776575943995},"8721055491415":{"naam":"Sentio Rose Espresso Unisex Eau de Parfum 100ml","ts":1776575944235},"6151027486491":{"naam":"NG Phenom Eau de Parfum 100ml + 15ml","ts":1776575944462},"8721055492870":{"naam":"SENTIO FEESTDAGEN 2 - Joy to the World - Eau de Parfum in Giftbag 50ml","ts":1776575944665},"7640158815717":{"naam":"Sentio Labris Eau De Parfum - 100 ml","ts":1776575944874},"8721055493976":{"naam":"Bubble Bliss - Fantastic Flamingo - Flap & Fly - Eau de Parfum - Voor Kinderen 15ml","ts":1776575945080},"8720938379277":{"naam":"Omerta - Daily Fresh Pack - set van 3x100ml","ts":1776575945273},"7640158818763":{"naam":"Sentio Miniparfum Cocktail - BLUE LAGOON - Eau de parfum For Her 15ml","ts":1776575945476},"7640158816158":{"naam":"Sentio Wish You The Best eau de parfum voor vrouwen - 15ml","ts":1776575945691},"7438235479408":{"naam":"NG DOMINATIO MEN 80 ML - Eau De Toilette","ts":1776575945895},"8719214754204":{"naam":"NG-Phenom-Eau de Parfum for Women 15ml","ts":1776575946113},"8715658401520":{"naam":"Linn Young - Ibiza Kiss Unisex - Eau de Parfum 100ml","ts":1776575946317},"6013913031041":{"naam":"NG Wild Men 100ml + 15ml Eau De Toilette","ts":1776575946519},"7640158819180":{"naam":"Vibezz Blissful Life parfum - Eau de parfum voor haar - 100ml","ts":1776575946938},"7640158816585":{"naam":"Sentio Zodiac - Aquarius - Waterman - Eau De Parfum - For Women - 15ml","ts":1776575947195},"8715658002512":{"naam":"Real Time - Free Sky For Woman - Eau De Parfum - 100Ml","ts":1776575947400},"8719214757519":{"naam":"NG Spectre Fragrances Gold Generation MEN For Men eau de toilette 100ml","ts":1776575947605},"8721055494515":{"naam":"Sentio Donut Drizzle eau de parfum unisex 15 ml","ts":1776575947802},"6291012905399":{"naam":"Dorall Quaint damesparfum eau de toilette 100 ml","ts":1776575948001},"8715658401124":{"naam":"Linn Young - Top Charms - Eau de parfum - 100ML","ts":1776575948203},"8721055492320":{"naam":"Vibezz Digital Dream - Eau de parfum voor dames - 100ml","ts":1776575948401},"8721055492931":{"naam":"Luxe Adventskalender Kerstboom met 24 mini Flesjes Eau de Parfum","ts":1776575948633},"8719214757472":{"naam":"NG Spectre Fragrances Alvino EL HOMBRE For Men eau de toilette 100ml","ts":1776575948843},"7640158816387":{"naam":"Sentio Blossoms of Joy Lovely miniparfum eau de parfum 15 ml.","ts":1776575949057},"8719214757342":{"naam":"NG Spectre Fragrances ALTHEA for her eau de parfum 100ml","ts":1776575949266},"8721055494140":{"naam":"Sentio Happy Birthday Giftset - Luxe parfum en showergel voor iedereen","ts":1776573127992},"5414666015844":{"naam":"Dorall -Always On My Mind- Eau de Toilette spray 100ml for women","ts":1776575949464},"8721055493075":{"naam":"SENTIO FEESTDAGEN 2 - Merry Christmas And Happy New Year - Eau de Parfum in leuke kerstbal 30ml","ts":1776575949673},"8715658999928":{"naam":"Linn Young - Work@holics For Men - Eau De Toilette - 100ML","ts":1776575949873},"8715658997702":{"naam":"Omerta Hatch Eau de Toilette 100ml","ts":1776575950078},"8715658400110":{"naam":"Linn Young - Gold Mine - Eau De Parfum - 100ML","ts":1776575950300},"8715658410157":{"naam":"Georges Mezotti-Blue Rain For Men Eau de Toilette 125ml","ts":1776575950516},"8721055499480":{"naam":"Luxe Kalender met 24 mini Flesjes Eau de Parfum (advent eventueel)","ts":1776575950716},"8715658390442":{"naam":"Linn Young - Club 420 City - Eau de toilette - 100ML","ts":1776575950928},"8719214755805":{"naam":"NG -Crystal Pink Giftset- 100ml Eau de Parfum 50ml Showergel 50ml Bodylotion","ts":1776575951131},"8714319228803":{"naam":"Amando - Mystery - Aftershave - Voor Mannen - 50 ml","ts":1775967660594},"6291012875807":{"naam":"Dorall Everscent Eau de Toilette voor dames - 100ml","ts":1776575951367},"8715658401650":{"naam":"Linn Young - Her Desire L'Absolu Women - Le parfum - 100ML","ts":1776575951574},"8715658401261":{"naam":"Linn Young - Oud Elixir d'Extase Black Label - Eau de parfum - 100ML","ts":1776659075878},"8715658380030":{"naam":"Omerta Omd Oh My Dear 100 ml - Eau De Parfum Spray Damesparfum","ts":1776659076084},"7640158817360":{"naam":"Sentio 200CC Eau De Parfum - 100 ml","ts":1776659076289},"8715658350507":{"naam":"Real Time - Smart Guy For Men - Eau de toilette - 100ML","ts":1776659076492},"8715658360162":{"naam":"Real Time - Tropical Cocktail - Eau de parfum - 100ML","ts":1776659076710},"8715658370598":{"naam":"Omerta - Mon Homme Revitalising Summer Elixir - Eau De Toilette - 100ML","ts":1776659076915},"8716516197968":{"naam":"Creascents Geurolie Exotic Lychee 750 Ml Transparant","ts":1776659077118},"5414666001953":{"naam":"Creation Lamis Catsuit Man 100 ml - Eau de Toilette - Herenparfum","ts":1776659077356},"8715658998952":{"naam":"Omerta Putting Green Eau de Toilette Pour Homme - 100ml","ts":1776659077558},"7640158816950":{"naam":"Hello Kitty - Giftset - Delicate Flower - Showergel + Eau de Parfum - Cadeauset voor Kinderen - Geschenkset","ts":1776659077764},"8721055498179":{"naam":"De La Mare Parfum Raggio Di Sole 73 Vanilla & Orchid Eau de Parfum 100 ml","ts":1776659077968},"8714319236709":{"naam":"Therme Geurstokjes Hammam 100 ml","ts":1776659078175},"8715658009238":{"naam":"Real Time Wonderful Woman Edp 100ml","ts":1776659078381},"8719214754495":{"naam":"Geurverspreider Vivance Sensual Shadows Allure of the night bergamot kaneel vanille met stokjes","ts":1775967663746},"8721055492382":{"naam":"Vibezz-Joy of Aqua-Eau de Parfum For Her-100ml","ts":1776659078581},"8715658420156":{"naam":"Georges Mezotti - Queen of Temptation Seduction - Eau de parfum 100ml","ts":1776659078783},"7640158819203":{"naam":"Vibezz-Infusion Noir-Eau de Parfum For Her-100ml","ts":1776659078980},"7640158815816":{"naam":"Sentio Parfum Universal For Woman Eau de Parfum for her 35ml","ts":1776659079202},"8719214756499":{"naam":"TBY - To Be Mythical - 100ml Eau de Toilette voor mannen","ts":1776659079405},"6013912035064":{"naam":"Egyptian Powder Luxury Set HORUS","ts":1776659079611},"7640158815830":{"naam":"Sentio Parfum Poppy Noir Eau de Parfum for her 35ml","ts":1776659079870},"7640158816738":{"naam":"Hello Kitty-Asia-15ml Eau de Parfum","ts":1776659080077},"8721055490678":{"naam":"Sentio Floricci Azzurro miniparfum eau de parfum 15ml","ts":1776659080273},"8719214752576":{"naam":"NG Embodiment of Style Women Eau de Parfum Spray 100 ml","ts":1776659080483},"8715658400370":{"naam":"Linn Young Coeur Noble - Eau de parfum - 100 ml","ts":1776659080700},"8715658390596":{"naam":"Linn Young - The One Beyond Black - Eau de toilette - 100ML","ts":1776659080901},"8715658350460":{"naam":"Real Time - British Blend For Men - Eau de toilette - 100ML","ts":1776659081109},"8715658002864":{"naam":"Real Time Eau de Toilette Kind Looks Man 100ml","ts":1776659081316},"6013917450497":{"naam":"Egyptian Powder HORUS 40gr + luxe borstel","ts":1776659081589},"8715658380696":{"naam":"Omerta - Rose Pure - Eau de Parfum - 100ml","ts":1776659081811},"6151029227221":{"naam":"Green Nature Aloe Vera pakket 4st.","ts":1776659082043},"8720938379314":{"naam":"Omerta - Signature Pack - set van 3x100ml","ts":1776659082247},"8715658380399":{"naam":"Omerta - Happy Love Fun For Women - Eau de parfum - 100ML","ts":1776659082457},"6291012002616":{"naam":"Creation Lamis Just Perfect Dream Giftset","ts":1776659082656},"6291012002685":{"naam":"Creation Lamis Savanna Nights Giftset","ts":1776659082880},"6291012002623":{"naam":"Creation Lamis Golden Wave Women Giftset","ts":1776659083094},"8719326174716":{"naam":"Creation Lamis - Catsuit Woman - Voordeelverpakking 3 stuks.","ts":1776659083308},"8721055490500":{"naam":"Sentio - mini parfum - My Number 1 - heren - vaderdag - eau de toilette - 15 ml","ts":1776659083517},"6291012871724":{"naam":"Creation Lamis - Achilles -  Eau de Toilette 100ml","ts":1776659083718},"5414666014274":{"naam":"Oriental Oud Arabi Parfum de Tiolette 100ml","ts":1776659083927},"8720938379291":{"naam":"Omerta - Wild energy Pack - set van 3x100ml","ts":1776659084386},"8721055493181":{"naam":"Hello Kitty - Parfum Set Van 6 Stuks - Eau de Parfum Voor Kinderen - 6x15ml","ts":1776659084606},"8719214750657":{"naam":"NG Delusional parfum - Eau de parfum voor de sensuele vrouw - 100 ml","ts":1776659084819},"8720938379239":{"naam":"Omerta - Night Out Pack - set van 3x100ml","ts":1776659100190},"8715658998426":{"naam":"Omerta - Silver & White Woman - Eau De Parfum - 100Ml","ts":1776659100391},"8715658390251":{"naam":"Linn Young \"Mighty Mood\" Eau de toilette 100ml","ts":1776659100600},"6151027359313":{"naam":"NG Predator for Women - 15ml - Eau de Parfum","ts":1776659100816},"8721055491781":{"naam":"Sentio Twirl Once More Eau de Parfum For Her 50ml","ts":1776659101064},"8715658400448":{"naam":"Linn Young Je suis Sure et Ceraine Bouquet de Fleurs 100ml","ts":1776659101273},"8720938379222":{"naam":"Omerta - Daily Elegance Pack - set van 3x100ml","ts":1776659101476},"6151009095048":{"naam":"NG Bella Vida Eau de Parfum 80 ml","ts":1776659101680},"7640158817490":{"naam":"SENTIO Cheers To The New Year Eau de Parfum - Kerst - Kerstparfum - Miniparfum 15 ml - Jasmijn Geur - Vanille geur - Bloemig","ts":1776659101888},"8715658390930":{"naam":"Linn Young Admiration Eternal Uomo - Eau de Toilette voor heren - 100ML","ts":1776659102095},"7640158817452":{"naam":"SENTIO Happy New Year Eau de Parfum 15 ml - Miniparfum - Kerst - Nieuw Jaar - Cacao - Fruitig Geur - Houtaard","ts":1776659102292},"6291012871731":{"naam":"Creation Lamis Fatal Snake Magical Giftset","ts":1776659102504},"8721055495741":{"naam":"Atelier Privee Mistical France parfum - Unisex eau de parfum met rozengeur - 100ml","ts":1776659102709},"8721055494287":{"naam":"Bubble Bliss Giftset Like a Fairytale-Eau de Parfum","ts":1776659102915},"6151028068092":{"naam":"Next Generation Home Perfume Bella Vida Spray - 200ml","ts":1776659103124},"8715658969617":{"naam":"Georges Mezotti - L'or - Eau De Parfum - 100ML","ts":1776659103333},"6291012005730":{"naam":"Creation Lamis -DIABLE BLEU- Unisex 100ml Eau de Toilette Spray","ts":1776659103552},"8719214753276":{"naam":"NG Bella Vida Giftset","ts":1776659103758},"8721055492726":{"naam":"SENTIO FEESTDAGEN PINK - Enchanting Glow - Eau de Parfum 50ml","ts":1776659103974},"8719214751104":{"naam":"Green Nature Aloe Vera Hand Cream 100ml","ts":1776659104182},"8715658400974":{"naam":"Linn Young -Oso Perfect Women Giftset- 100ml + 30ml Eau de Parfum","ts":1776659104385},"8718421831555":{"naam":"NG Touch! / Eau de parfum / 80 ml","ts":1776659104584},"7640158818749":{"naam":"Sentio Miniparfum Cocktail - PINA COLADA - Eau de parfum For Her 15ml","ts":1776659104805},"8721055491378":{"naam":"Sentio Peachy Twist Unisex Eau de Parfum 100ml","ts":1776659105030},"8721055495802":{"naam":"Atelier Privee Mistical France Unisex - Dark Valor - Eau de Parfum - 100ml","ts":1776659105228},"7640158819258":{"naam":"Vibezz-Solitude-Eau de Toilette For Him-100ml","ts":1776659105452},"8719214755843":{"naam":"NG goldigger men set edt 100 ml + shower gel 50 ml + after shave 50 ml","ts":1776659105690},"8719214756529":{"naam":"TBY - To Be Talented - 100ml Eau de Toilette voor mannen","ts":1776659105901},"8715658998631":{"naam":"Linn Young - Dangerzone - Eau De Parfum - 100ML","ts":1776659106313},"8719214750084":{"naam":"NG Home -Crystal Pink - Geurstokjes 200ml","ts":1776659106518},"7640158816776":{"naam":"Hello Kitty-Fashion stylist!-15ml Eau de Parfum","ts":1776659106733},"5414666001557":{"naam":"Catsuit Woman - Eau de Toilette - 100 ml","ts":1776659106951},"8721055490517":{"naam":"Sentio - mini parfum - I love You - heren - vaderdag - eau de toilette - 15 ml","ts":1776659107151},"8715658370017":{"naam":"Omerta - Silver Ocean Blue - EDT men - 100 ml","ts":1776659107382},"8719214757229":{"naam":"NG Dark Elixir Men Eau de Toilette 100 ml","ts":1776659107595},"8715658360025":{"naam":"Real Time Black Emotion for women edp 100ml","ts":1776659107819},"8715658350705":{"naam":"Real Time - Me Time - Eau de Toilette - 100Ml","ts":1776659108030},"8721055493242":{"naam":"Hello Kitty-Once Upon a Time-15ml Eau de Parfum","ts":1776659108263},"8721055493136":{"naam":"Hello Kitty-Watermelon Scent-15ml Eau de Parfum","ts":1776659108476},"8715658410171":{"naam":"Georges Mezotti-Blue Rain Sport For Men Eau de Toilette 125ml","ts":1776659108889},"6291012878259":{"naam":"Dorall -Miss Blossom- Eau de Parfum 100ml","ts":1776659109090},"8715658013136":{"naam":"Street Looks - La Creation Pour Homme - Eau de toilette - 100ML","ts":1776659109307},"7640158814987":{"naam":"Sentio Involved Eau de Toilette - 100 ml","ts":1776573069972},"8721055496991":{"naam":"De La Mare Strawberry - Aardbei Geur - For Women Eau de Parfum 15 ml","ts":1776659109513},"8721055497028":{"naam":"De La Mare Pistachio parfum - Pistache geur eau de parfum voor vrouwen - 15 ml","ts":1776659109740},"8715658401001":{"naam":"Linn Young -Rosiale Paris- Giftset 100ml + 30ml Eau de Parfum","ts":1776659109942},"8715658998464":{"naam":"Omerta Black & Silver Man Eau de Toilette 100ml","ts":1776659110158},"8715658390947":{"naam":"Linn Young Admiration Eternal Uomo L'assoluto - Eau de Toilette voor heren - 100ML","ts":1776659110372},"8719214757052":{"naam":"NG - SHE IS HERE - 100ml Eau de Parfum for Women","ts":1776659110572},"8719326174709":{"naam":"Creation Lamis Catsuit Man - Topparfum voor de zelfverzekerde man - 3 stuks","ts":1776659160676},"8721055492689":{"naam":"SENTIO Love & Joy Eau de Parfum 15 ml - Miniparfum - Love - Citrus - Fruitig - Unisex","ts":1776659160886},"8715658400523":{"naam":"Linn - Young Oui Je T'Aime Pour Toujours - Eau De Parfum - 100Ml","ts":1776659161108},"8715658360001":{"naam":"Real Time - Nuit Charmante - Eau de parfum - 100ML","ts":1776659161325},"7640158816509":{"naam":"Sentio Zodiac - Gemini - Tweeling - Eau De Parfum - For Women - 15ml","ts":1776659161529},"8719214756512":{"naam":"TBY - To Be Successful - 100ml Eau de Toilette voor mannen","ts":1776659161744},"8715658350262":{"naam":"Real TimeFijn Goud 999.9 Voor Mannen Eau de Toilette Spray 100ml","ts":1776659161951},"8721055493921":{"naam":"Bubble Bliss - Fantastic Flamingo - Pink Paradise - Eau de Parfum - Voor Kinderen 15ml","ts":1776659162154},"8718421831227":{"naam":"NG Heaven's Smell Eau de Parfum 100 ml","ts":1776659162364},"7640158819197":{"naam":"Vibezz-Confermato-Eau de Parfum For Her-100ml","ts":1776659162569},"8721055491453":{"naam":"Sentio Soft Suede Eau de Parfum 100ml","ts":1776659162814},"8719214753313":{"naam":"Next Generation Next Fragrance Eau de Parfum 100ml","ts":1776659163032},"8718421831234":{"naam":"NG Red Force for Men - 100 ml - Eau de Toilette","ts":1776659163250},"8719214752354":{"naam":"NG Eau de Parfum Mrs Perfect 100 ml","ts":1776659163457},"8719214753344":{"naam":"NG Heaven's Body Men Eau de Toilette 100ml -Voor Mannen.","ts":1776659163671},"8719214751661":{"naam":"NG Eau de Toilette L Odeur Men 100 ml","ts":1776659163881},"8719214757366":{"naam":"NG Spectre Fragrances FONZA for her eau de parfum 100ml","ts":1776659164108},"8719214758356":{"naam":"NG Elinne Eau de Parfum - 90ml","ts":1776659164327},"8719214758363":{"naam":"NG Lightness Eau de Parfum 100ml","ts":1776659164564},"8718421831913":{"naam":"NG Nightly Desire Eau de Toilette 100 ml","ts":1776659164770},"8719214757755":{"naam":"NG -Wild Men Giftset- 100ml Eau de Toilette-50ml Showergel-50ml Aftershave balm","ts":1776659164977},"8719214755829":{"naam":"NG -Next Fragranse For Her- 100ml Eau de Parfum-50ml Showergel-50ml Bodylotion","ts":1776659165190},"8715658360070":{"naam":"Real Time Trespassing Lady Eau de Parfum 100ml","ts":1776659165416},"8721055493358":{"naam":"Hello Kitty Club Eau de Parfum voor Kinderen 50 ml - I'm the rainbow after the storm","ts":1776573186021},"8719214751654":{"naam":"NG L'Odeur Women Eau de Parfum Spray 100 ml","ts":1776659230837},"8715658009115":{"naam":"Real Time - Si Femme Charme - Eau De Parfum - 100ML","ts":1776659165630},"8715658003526":{"naam":"Real Time Leave My Lover Purple Eau de Parfum 100ml","ts":1776659166049},"5414666016452":{"naam":"Creation Lamis - Espy - Eau de Parfum 100ml","ts":1776659166263},"8715658360964":{"naam":"Real Time - Yes Call Me - Eau de parfum - 100ML","ts":1776659166489},"8720938379260":{"naam":"Omerta - Seduction Pack - set van 3x100ml","ts":1776659166701},"8721055490012":{"naam":"Sentio Pink Grenade Eau De Parfum - 100 ml","ts":1776659166910},"8715658380368":{"naam":"Omerta - Invasion Third Dimension - Eau De Parfum - 100Ml","ts":1776659167115},"8719214754464":{"naam":"Geurstokjes Vivance - BLOSSOM VEIL - 200ml met twisted fragrance sticks","ts":1775967787240},"8719214754471":{"naam":"Geurverspreider Vivance - ORCHARD EMBRACE - 200ml met twisted fragrance sticks","ts":1775967787469},"8719214754457":{"naam":"Geurstokjes Vivance - NUDE PURITY - 200ml met twisted fragrance sticks","ts":1775967787760},"6013907728742":{"naam":"Georges Mezotti - Blue Rain - For Men 3 x 125ml","ts":1776659167325},"8715658370215":{"naam":"Omerta - Faktz Select - Eau De Toilette - 100Ml","ts":1776659167571},"8718421831562":{"naam":"NG Crystal Pink Eau de Parfum 100 ml","ts":1776659167783},"8715658400530":{"naam":"Oui Je T'aime! Ma Cherie Eau De Parfum 100ml","ts":1776659167987},"8719214750053":{"naam":"NG Crystal Pink Eau de Parfum 100 ml + 15ml Dames","ts":1776659168194},"8715658370154":{"naam":"Omerta - Acqua Di Omerta - Eau De Toilette - 100ML","ts":1776659168445},"5414666011471":{"naam":"Creation Lamis - Golden Wave - Eau de Parfum 100ml","ts":1776659168663},"8715658370161":{"naam":"Blue Beach Intense for him by Omerta","ts":1776659168880},"8715658997733":{"naam":"Omerta - Couture Cat - Eau De Parfum - 100ML","ts":1776659169089},"8715658998969":{"naam":"Omerta - Free & Mysterious Pour Femme - Eau De Parfum - 100ML","ts":1776659169303},"8715658999034":{"naam":"Omerta Stand In Man - Eau de Toilette voor heren - 100ml","ts":1776659169507},"8719214750817":{"naam":"NG-Touch- Eau de Parfum for Women 15ml","ts":1776659169724},"8715658380412":{"naam":"Omerta - Out Of Question - Eau de parfum - 100ML","ts":1776659169930},"6291012002692":{"naam":"Creation Lamis Arrivederci Giftset","ts":1776659170149},"8718421831197":{"naam":"NG Predator for Women - 100 ml - Eau de Parfum","ts":1776659170352},"8715658998617":{"naam":"Clouds of Love Man eau de toilette  100 ML","ts":1776659170583},"8715658360155":{"naam":"Real Time Eau de Parfum Tropical Sun","ts":1776659170790},"8721055493860":{"naam":"Bubble Bliss - Unicorn Sprinkles - Discover - Lika a Unicorn - eau de parfum - voor kinderen 15ml","ts":1776659170990},"8721055494225":{"naam":"Bubble Bliss - Like a Fairytale - Lovely Lily - Eau de Parfum - Prinsessen Voor Kinderen 15ml","ts":1776659171823},"8715658380931":{"naam":"Omerta - Pink Shoe - Eau de Parfum 100ml","ts":1776659221935},"8715658999430":{"naam":"Omerta Love Feathers - Eau de parfum - 100ML","ts":1776659222336},"6291012002678":{"naam":"Creation Lamis Ruler Giftset","ts":1775967842712},"6291012874381":{"naam":"Dorall Twilight Wilderness - Herenparfum eau de toilette - 100 ml","ts":1776575888994},"8715658350521":{"naam":"Real Time Hunted For Men - eau de toilette voor heren - 100ML","ts":1776575946732},"8715658370086":{"naam":"Omerta - Big Release The Mood - EDT men - 100ml","ts":1776659222540},"8721055494263":{"naam":"Bubble Bliss - Like a Fairytale - Glimmering Grace - Eau de Parfum - Prinsessen Voor Kinderen 15ml","ts":1776659222747},"8720938379345":{"naam":"Omerta - Golden challenge EDT men 100 ml","ts":1776659222958},"7640158816691":{"naam":"Hello Kitty-Cotton Candy- suikerspin - 15ml Eau de Parfum","ts":1776659223170},"8715658380351":{"naam":"Omerta - Invasion - Eau De Parfum - 100Ml","ts":1776659223369},"7640158816677":{"naam":"Hello Kitty-Peach-15ml Eau de Parfum","ts":1776659223577},"6291012002661":{"naam":"Creation Lamis Golden Wave for Men Giftset","ts":1776659084175},"8715658370505":{"naam":"Omerta - L'uomo X - Eau De Toilette - 100ML","ts":1776659223805},"7640158816653":{"naam":"Hello Kitty-Vanilla-15ml Eau de Parfum","ts":1776659224021},"8715658380221":{"naam":"Omerta - Oh So Black For Women - Eau De Parfum - 100ML","ts":1776659224228},"8721055494270":{"naam":"Bubble Bliss - Like a Fairytale - Magical Mae - Eau de Parfum - Prinsessen Voor Kinderen 15ml","ts":1776659224427},"8721055494232":{"naam":"Bubble Bliss - Like a Fairytale - Dreamy Daisy - Eau de Parfum - Prinsessen Voor Kinderen 15ml","ts":1776659224648},"8721055493891":{"naam":"Bubble Bliss - Unicorn Sprinkles - Sparkle- Lika a Unicorn - eau de parfum - voor kinderen 15ml","ts":1776659224905},"8720938379352":{"naam":"Omerta - Twice so nice - Eau de parfum - 100ml","ts":1776659225123},"8715658370369":{"naam":"Omerta -Royal X Red- 100ml Eau de Toilette for men","ts":1776659225322},"7640158816714":{"naam":"Hello Kitty-Apple-15ml Eau de Parfum","ts":1776659225542},"8715658999638":{"naam":"Omerta Clouds of Love Eau de Parfum 100ml","ts":1776659225777},"8715658370543":{"naam":"Omerta - Conclude Oud Extreme Attraction - Eau De Parfum - 100ML","ts":1776659225989},"7640158816615":{"naam":"Hello Kitty-Coconut-15ml Eau de Parfum","ts":1776659226215},"8721055493211":{"naam":"Hello Kitty-Rainbow-15ml Eau de Parfum","ts":1776659226434},"8715658380757":{"naam":"Omerta -Ladies World- Eau de Parfum 100ml","ts":1776659226640},"7640158816790":{"naam":"Hello Kitty-Girl Gang-15ml Eau de Parfum","ts":1776659226849},"7640158816639":{"naam":"Hello Kitty-Strawberry-15ml Eau de Parfum","ts":1776659227052},"8715658380405":{"naam":"Omerta -Lazy Nights- Eau de Parfum 100ml","ts":1776659227257},"8715658380672":{"naam":"Omerta -Shoe Red- Eau de Parfum 100ml","ts":1776659227467},"8721055493884":{"naam":"Bubble Bliss - Unicorn Sprinkles - Embrace - Lika a Unicorn - eau de parfum - voor kinderen 15ml","ts":1776659227675},"8715658999249":{"naam":"Omerta Sensible Man 100ml Eau de Toilette","ts":1776659227939},"8715658380115":{"naam":"Omerta - Love Dust - Eau De Parfum - 100ML","ts":1776659228139},"8715658998839":{"naam":"Omerta - Express Sensualite Energy - Eau De Parfum - 100ML","ts":1776659228357},"8721055493440":{"naam":"Hello Kitty - Giftset - Kisses - Showergel + Eau de Parfum - Cadeauset voor Kinderen - Geschenkset","ts":1776659106111},"7640158816837":{"naam":"Hello Kitty-Spring Time-15ml Eau de Parfum","ts":1776659228572},"7640158816813":{"naam":"Hello Kitty-I feel so pretty today!-15ml Eau de Parfum","ts":1776659228776},"8715658997993":{"naam":"Omerta - Golden Challenge Ladies World - Eau De Parfum - 100ML","ts":1776659228981},"8721055493853":{"naam":"Bubble Bliss - Unicorn Sprinkles - Smile - Lika a Unicorn - eau de parfum - voor kinderen 15ml","ts":1776659229194},"8721055493877":{"naam":"Bubble Bliss - Unicorn Sprinkles - Shine - Lika a Unicorn - eau de parfum - voor kinderen 15ml","ts":1776659229404},"8721055493303":{"naam":"Hello Kitty You're Cute Eau de Parfum voor Kinderen 50ml","ts":1776659108684},"8715658380665":{"naam":"Omerta -Shoe Blue- Eau de Parfum 100ml","ts":1776659229611},"8721055493198":{"naam":"Hello Kitty-Best Friend-15ml Eau de Parfum","ts":1776659229812},"8715658370437":{"naam":"Omerta -Golden Challenge Elixer- 100ml Eau de Toilette for men","ts":1776659230011},"8721055493228":{"naam":"Hello Kitty-You Are Cute-15ml Eau de Parfum","ts":1776659230242},"5414666014427":{"naam":"Creation Lamis Just Perfect Dream for her - Eau de parfum met bloemige noten - 100ml","ts":1776659230444},"8715658380658":{"naam":"Omerta Invasion Awakening - Vrouwelijke eau de parfum - 100ml","ts":1776659231041},"8715658370062":{"naam":"Omerta Meet Me On The Wild Site Eau de Toilette 100ml","ts":1776659231245},"8715658380580":{"naam":"Omerta - La Donna X - Eau De Parfum - for women - 100ML","ts":1776659231445},"8715658350866":{"naam":"Real Time - Submarine Elixir - Eau de toilette - 100ML","ts":1776659074835},"8715658350873":{"naam":"Real Time - Ad Vitam Aeternam Elixir Extreme - Eau de toilette - 100ML","ts":1776659075465},"8721055493501":{"naam":"DLM Lumi Bloom - 100ml Eau de Parfum","ts":1776659074375},"8721055493549":{"naam":"DLM Pink Dreams - 100ml Eau de Parfum","ts":1776659074631},"8721055493587":{"naam":"DLM Soft Touch - 100ml Eau de Parfum","ts":1776659075040},"8721055493563":{"naam":"DLM Rose Reverie - 100ml Eau de Parfum","ts":1776659075672},"8721055493662":{"naam":"8721055493662","ts":1776159805668},"8721055493600":{"naam":"8721055493600","ts":1776159805830},"6291012007307":{"naam":"6291012007307","ts":1776159805994},"8721055493525":{"naam":"8721055493525","ts":1776159806165},"8721055493624":{"naam":"8721055493624","ts":1776159806362},"8716516197944":{"naam":"Geurolie Cotton 750 Ml Transparant","ts":1776187178244},"8716516197951":{"naam":"Musk & Wood Geurolie - 750 ML","ts":1776187178393},"8721349102621":{"naam":"Vibezz-Lush x Echo-Eau de Parfum For Her-100ml","ts":1776399646406},"8328956809990":{"naam":"Amando - Mystery - Eau de Toilette - Spray - Voor Mannen - 50 ml - Voordeelverpakking - 4 stuks","ts":1776399646587},"8721349102645":{"naam":"Vibezz-Delylu-Eau de Parfum For Her-100ml","ts":1776399646739},"8322179663674":{"naam":"Amando - Mystery - Eau de Toilette - Spray - Voor Mannen - 50 ml - Voordeelverpakking - 2 stuks","ts":1776399646889},"8721349102614":{"naam":"Atelier Privee - GOLDEN SAND VULIGNON - 100ml Eau de Parfum Unisex","ts":1776486963535},"8721349102584":{"naam":"Atelier Privee - DREAMY RIVER VULIGNON - 100ml Eau de Parfum Unisex","ts":1776486963734},"8721349102591":{"naam":"Atelier Privee - SUNSET SKYLINE VULIGNON - 100ml Eau de Parfum Unisex","ts":1776486963930},"8721349102607":{"naam":"Atelier Privee - WHISPER PALMS - 100ml Eau de Parfum Unisex","ts":1776486964148},"8714319258763":{"naam":"Therme Home Perfume Sticks Zen White Lotus - 150 ml","ts":1776573186411},"8719214752569":{"naam":"NG - VANEZIA - for Women 100 ml Eau de Parfum","ts":1776659075252},"7640158818107":{"naam":"Sentio Rojo 045 Giftset - Unisex Eau de Parfum (100ml) & Showergel - Luxe Houtachtige Geur","ts":1776743813528},"8719214752361":{"naam":"NG Eau de Parfum XII Chic Rouge 100 ml","ts":1776743813692},"8719214752347":{"naam":"NG To be Mine Men Eau de Toilette Spray 100 ml","ts":1776743813834},"8715658361657":{"naam":"Real Time - Roman Empire - Eau de parfum - 100ML","ts":1776743813968},"8715658361664":{"naam":"Real Time - Roman Empire L'Assoluto - Eau de parfum - 100ML","ts":1776743814106},"8715658350811":{"naam":"Real Time - Roman Empire - Eau de toilette - 100ML","ts":1776743814244}}